Workbook

Sheet Resultado
A1: URL API (ngrok)
A2: Resultado ultima ejecucion
A3: Estado | B3: Pedido Dynamics | C3: Fecha de ejecución | D3: Usuario | E3: Error

Sheet Instrucciones Dynamics
A1: SUBIR ORDENES DE VENTA A DYNAMICS (Marketing)
A3: 1. Arranque dynamics-integration (run.ps1) y ngrok http 8080
A4: 2. Pegue la URL https de ngrok en Resultado!B1
A5: 3. En Excel web: Automatizar > Nuevo script > pegar dist/ProbarConexion.osts.ts
A6: 4. Repita con dist/SubirMarketing.osts.ts (boton Subir pedidos)
A8: CAPTURA (como siempre):
A9: - Costco: Tabla3 con Cuenta Dynamics (ej. C0010), codigo en Dynamics, Cantidad, Ov vacia
A10: - E-commerce: Tabla4 igual; si no hay Cuenta Dynamics, use columna Cliente con el codigo
A11: - El nombre del cliente puede quedar en otra columna; Dynamics exige cuenta (C00xx)
A13: SUBIR:
A14: - Probar conexion
A15: - Subir pedidos marketing (todas las filas pendientes de Costco y E-commerce)
A17: El numero OV se escribe en Ov / Orden de venta y queda en Historial.

Sheet Costco
A1: Fecha | B1: Plataforma | C1: PO | D1: Orden | E1: Cliente | F1: Dynamics | G1: Producto | H1: Cantidad | I1: Costo | J1: Subtotal | K1: Envío | L1: Total | M1: Ov | N1: Guía
A2: =TODAY() | B2: Costco | E2: Ms. EVA SUSANA CONZUELO GONZALEZ | F2: =_xlfn.XLOOKUP(Tabla3[[#This Row],[Producto ]],'Form C'!A:A,'Form C'!B:B,1,0) | G2: JustFx 120 Capsulas | H2: 1 | I2: =_xlfn.XLOOKUP(Tabla3[[#This Row],[Dynamics]],'Form C'!B:B,'Form C'!D:D,0,0) | J2: =$H2*$I2 | K2: =_xlfn.XLOOKUP(Tabla3[[#This Row],[Plataforma]],'Form C'!E:E,'Form C'!F:F,0,0,1) | L2: =J2+K2
A3: =TODAY() | B3: Costco | F3: =_xlfn.XLOOKUP(Tabla3[[#This Row],[Producto ]],'Form C'!A:A,'Form C'!B:B,1,0) | I3: =_xlfn.XLOOKUP(Tabla3[[#This Row],[Dynamics]],'Form C'!B:B,'Form C'!D:D,0,0) | J3: =$H3*$I3 | K3: =_xlfn.XLOOKUP(Tabla3[[#This Row],[Plataforma]],'Form C'!E:E,'Form C'!F:F,0,0,1) | L3: =J3+K3
A4: =TODAY() | B4: Costco | F4: =_xlfn.XLOOKUP(Tabla3[[#This Row],[Producto ]],'Form C'!A:A,'Form C'!B:B,1,0) | I4: =_xlfn.XLOOKUP(Tabla3[[#This Row],[Dynamics]],'Form C'!B:B,'Form C'!D:D,0,0) | J4: =$H4*$I4 | K4: =_xlfn.XLOOKUP(Tabla3[[#This Row],[Plataforma]],'Form C'!E:E,'Form C'!F:F,0,0,1) | L4: =J4+K4
A5: =TODAY() | B5: Costco | F5: =_xlfn.XLOOKUP(Tabla3[[#This Row],[Producto ]],'Form C'!A:A,'Form C'!B:B,1,0) | I5: =_xlfn.XLOOKUP(Tabla3[[#This Row],[Dynamics]],'Form C'!B:B,'Form C'!D:D,0,0) | J5: =$H5*$I5 | K5: =_xlfn.XLOOKUP(Tabla3[[#This Row],[Plataforma]],'Form C'!E:E,'Form C'!F:F,0,0,1) | L5: =J5+K5
A6: =TODAY() | B6: Costco | F6: =_xlfn.XLOOKUP(Tabla3[[#This Row],[Producto ]],'Form C'!A:A,'Form C'!B:B,1,0) | I6: =_xlfn.XLOOKUP(Tabla3[[#This Row],[Dynamics]],'Form C'!B:B,'Form C'!D:D,0,0) | J6: =$H6*$I6 | K6: =_xlfn.XLOOKUP(Tabla3[[#This Row],[Plataforma]],'Form C'!E:E,'Form C'!F:F,0,0,1) | L6: =J6+K6
A7: =TODAY() | B7: Costco | F7: =_xlfn.XLOOKUP(Tabla3[[#This Row],[Producto ]],'Form C'!A:A,'Form C'!B:B,1,0) | I7: =_xlfn.XLOOKUP(Tabla3[[#This Row],[Dynamics]],'Form C'!B:B,'Form C'!D:D,0,0) | J7: =$H7*$I7 | K7: =_xlfn.XLOOKUP(Tabla3[[#This Row],[Plataforma]],'Form C'!E:E,'Form C'!F:F,0,0,1) | L7: =J7+K7
A8: =TODAY() | B8: Costco | F8: =_xlfn.XLOOKUP(Tabla3[[#This Row],[Producto ]],'Form C'!A:A,'Form C'!B:B,1,0) | I8: =_xlfn.XLOOKUP(Tabla3[[#This Row],[Dynamics]],'Form C'!B:B,'Form C'!D:D,0,0) | J8: =$H8*$I8 | K8: =_xlfn.XLOOKUP(Tabla3[[#This Row],[Plataforma]],'Form C'!E:E,'Form C'!F:F,0,0,1) | L8: =J8+K8
A9: =TODAY() | B9: Costco | F9: =_xlfn.XLOOKUP(Tabla3[[#This Row],[Producto ]],'Form C'!A:A,'Form C'!B:B,1,0) | I9: =_xlfn.XLOOKUP(Tabla3[[#This Row],[Dynamics]],'Form C'!B:B,'Form C'!D:D,0,0) | J9: =$H9*$I9 | K9: =_xlfn.XLOOKUP(Tabla3[[#This Row],[Plataforma]],'Form C'!E:E,'Form C'!F:F,0,0,1) | L9: =J9+K9
A10: =TODAY() | B10: Costco | F10: =_xlfn.XLOOKUP(Tabla3[[#This Row],[Producto ]],'Form C'!A:A,'Form C'!B:B,1,0) | I10: =_xlfn.XLOOKUP(Tabla3[[#This Row],[Dynamics]],'Form C'!B:B,'Form C'!D:D,0,0) | J10: =$H10*$I10 | K10: =_xlfn.XLOOKUP(Tabla3[[#This Row],[Plataforma]],'Form C'!E:E,'Form C'!F:F,0,0,1) | L10: =J10+K10
A11: =TODAY() | F11: =_xlfn.XLOOKUP(Tabla3[[#This Row],[Producto ]],'Form C'!A:A,'Form C'!B:B,1,0) | I11: =_xlfn.XLOOKUP(Tabla3[[#This Row],[Dynamics]],'Form C'!B:B,'Form C'!D:D,0,0) | J11: =$H11*$I11 | K11: =_xlfn.XLOOKUP(Tabla3[[#This Row],[Plataforma]],'Form C'!E:E,'Form C'!F:F,0,0,1) | L11: =J11+K11
A12: =TODAY() | F12: =_xlfn.XLOOKUP(Tabla3[[#This Row],[Producto ]],'Form C'!A:A,'Form C'!B:B,1,0) | I12: =_xlfn.XLOOKUP(Tabla3[[#This Row],[Dynamics]],'Form C'!B:B,'Form C'!D:D,0,0) | J12: =$H12*$I12 | K12: =_xlfn.XLOOKUP(Tabla3[[#This Row],[Plataforma]],'Form C'!E:E,'Form C'!F:F,0,0,1) | L12: =J12+K12
A13: =TODAY() | F13: =_xlfn.XLOOKUP(Tabla3[[#This Row],[Producto ]],'Form C'!A:A,'Form C'!B:B,1,0) | I13: =_xlfn.XLOOKUP(Tabla3[[#This Row],[Dynamics]],'Form C'!B:B,'Form C'!D:D,0,0) | J13: =$H13*$I13 | K13: =_xlfn.XLOOKUP(Tabla3[[#This Row],[Plataforma]],'Form C'!E:E,'Form C'!F:F,0,0,1) | L13: =J13+K13
A14: =TODAY() | F14: =_xlfn.XLOOKUP(Tabla3[[#This Row],[Producto ]],'Form C'!A:A,'Form C'!B:B,1,0) | I14: =_xlfn.XLOOKUP(Tabla3[[#This Row],[Dynamics]],'Form C'!B:B,'Form C'!D:D,0,0) | J14: =$H14*$I14 | K14: =_xlfn.XLOOKUP(Tabla3[[#This Row],[Plataforma]],'Form C'!E:E,'Form C'!F:F,0,0,1) | L14: =J14+K14
A15: =TODAY() | F15: =_xlfn.XLOOKUP(Tabla3[[#This Row],[Producto ]],'Form C'!A:A,'Form C'!B:B,1,0) | I15: =_xlfn.XLOOKUP(Tabla3[[#This Row],[Dynamics]],'Form C'!B:B,'Form C'!D:D,0,0) | J15: =$H15*$I15 | K15: =_xlfn.XLOOKUP(Tabla3[[#This Row],[Plataforma]],'Form C'!E:E,'Form C'!F:F,0,0,1) | L15: =J15+K15
A16: =TODAY() | F16: =_xlfn.XLOOKUP(Tabla3[[#This Row],[Producto ]],'Form C'!A:A,'Form C'!B:B,1,0) | I16: =_xlfn.XLOOKUP(Tabla3[[#This Row],[Dynamics]],'Form C'!B:B,'Form C'!D:D,0,0) | J16: =$H16*$I16 | K16: =_xlfn.XLOOKUP(Tabla3[[#This Row],[Plataforma]],'Form C'!E:E,'Form C'!F:F,0,0,1) | L16: =J16+K16
A17: =TODAY() | F17: =_xlfn.XLOOKUP(Tabla3[[#This Row],[Producto ]],'Form C'!A:A,'Form C'!B:B,1,0) | I17: =_xlfn.XLOOKUP(Tabla3[[#This Row],[Dynamics]],'Form C'!B:B,'Form C'!D:D,0,0) | J17: =$H17*$I17 | K17: =_xlfn.XLOOKUP(Tabla3[[#This Row],[Plataforma]],'Form C'!E:E,'Form C'!F:F,0,0,1) | L17: =J17+K17
A18: =TODAY() | F18: =_xlfn.XLOOKUP(Tabla3[[#This Row],[Producto ]],'Form C'!A:A,'Form C'!B:B,1,0) | I18: =_xlfn.XLOOKUP(Tabla3[[#This Row],[Dynamics]],'Form C'!B:B,'Form C'!D:D,0,0) | J18: =$H18*$I18 | K18: =_xlfn.XLOOKUP(Tabla3[[#This Row],[Plataforma]],'Form C'!E:E,'Form C'!F:F,0,0,1) | L18: =J18+K18
A19: =TODAY() | F19: =_xlfn.XLOOKUP(Tabla3[[#This Row],[Producto ]],'Form C'!A:A,'Form C'!B:B,1,0) | I19: =_xlfn.XLOOKUP(Tabla3[[#This Row],[Dynamics]],'Form C'!B:B,'Form C'!D:D,0,0) | J19: =$H19*$I19 | K19: =_xlfn.XLOOKUP(Tabla3[[#This Row],[Plataforma]],'Form C'!E:E,'Form C'!F:F,0,0,1) | L19: =J19+K19
A20: =TODAY() | F20: =_xlfn.XLOOKUP(Tabla3[[#This Row],[Producto ]],'Form C'!A:A,'Form C'!B:B,1,0) | I20: =_xlfn.XLOOKUP(Tabla3[[#This Row],[Dynamics]],'Form C'!B:B,'Form C'!D:D,0,0) | J20: =$H20*$I20 | K20: =_xlfn.XLOOKUP(Tabla3[[#This Row],[Plataforma]],'Form C'!E:E,'Form C'!F:F,0,0,1) | L20: =J20+K20
A21: =TODAY() | F21: =_xlfn.XLOOKUP(Tabla3[[#This Row],[Producto ]],'Form C'!A:A,'Form C'!B:B,1,0) | I21: =_xlfn.XLOOKUP(Tabla3[[#This Row],[Dynamics]],'Form C'!B:B,'Form C'!D:D,0,0) | J21: =$H21*$I21 | K21: =_xlfn.XLOOKUP(Tabla3[[#This Row],[Plataforma]],'Form C'!E:E,'Form C'!F:F,0,0,1) | L21: =J21+K21

Sheet Form C
A1: Plataforma | B1: Código | C1: Precio | D1: Precio actualizado
A2: Costco | E2: costco | F2: 0
A3: JustFx 120 Capsulas | B3: 503635000705 | C3: 308.89 | D3: 337.46 | E3: =D3-C3-1
A4: JustBio H 110 Gomitas | B4: 503635001600 | C4: 252.25 | D4: 278.27 | E4: =D4-C4-1
A5: JustCollagen 180 Tabletas | B5: 503635002600 | C5: 225.22 | D5: 248.45 | E5: =D5-C5-1
A6: Justcetrux 180 Tabs Vitamina C Olnatura | B6: 503635003900 | C6: 167.38 | D6: 133 | E6: =D6-C6-1
A7: TN Probióticos 180 Caps | B7: 503635001402 | C7: 281.38 | D7: 332.92 | E7: =D7-C7-1
A8: Colágeno Tipo II 90 Cápsulas | B8: 503635000606 | C8: 682.24 | D8: 682.24 | E8: =D8-C8-1
A9: JustBiotics 110 Gomitas Probioticos | B9: 503635002000 | C9: 231.02 | D9: 254.86 | E9: =D9-C9-1
A10: Glucosamina + Condroitina | B10: 503635000300 | C10: 555.32 | D10: 633.97 | E10: =D10-C10-1
A11: Justvika 120 Caps | B11: 503635002300 | C11: 161.04

Sheet E-commerce
A1: Fecha | B1: Mercado Libre | C1: Columna1 | D1: Fecha de compra | E1: N° venta | F1: Orden | G1: Cliente | H1: Dynamics | I1: Título de la publicación | J1: Producto | K1: Cantidad | L1: Costo exc | M1: Costo | N1: Subtotal | O1: Envío | P1: Total | Q1: Orden de venta | R1: Guía | S1: DESCUENTO
A2: 28 de mayo de 2026 23:30 hs. | B2: Mercado Libre | D2: 28 de mayo de 2026 23:30 hs. | E2: 2000013227330657 | G2: Arturo Castellanos | H2: =+_xlfn.XLOOKUP(Tabla4[[#This Row],[Título de la publicación]],ML!C:C,ML!A:A,1,0,1) | I2: Isoflavonas Olnatura Just 90 Tabletas | J2: =+_xlfn.XLOOKUP(Tabla4[[#This Row],[Dynamics]],ML!A:A,ML!B:B,1,0,1) | K2: 1 | M2: =+_xlfn.XLOOKUP(Tabla4[[#This Row],[Dynamics]],ML!A:A,ML!E:E,1,0,1) | N2: =Tabla4[[#This Row],[Cantidad]]*Tabla4[[#This Row],[Costo ]] | P2: =Tabla4[[#This Row],[Subtotal]]+Tabla4[[#This Row],[Envío]] | Q2: OV0028020 | R2: MEL47173044627FMXDF01
A3: 28 de mayo de 2026 20:27 hs. | B3: Mercado Libre | D3: 28 de mayo de 2026 20:27 hs. | E3: 2000013225451755 | G3: Raquel Gleason | H3: =+_xlfn.XLOOKUP(Tabla4[[#This Row],[Título de la publicación]],ML!C:C,ML!A:A,1,0,1) | I3: Just Omega 3 120 Gomitas Olnatura Mandarina | J3: =+_xlfn.XLOOKUP(Tabla4[[#This Row],[Dynamics]],ML!A:A,ML!B:B,1,0,1) | K3: 1 | M3: =+_xlfn.XLOOKUP(Tabla4[[#This Row],[Dynamics]],ML!A:A,ML!E:E,1,0,1) | N3: =Tabla4[[#This Row],[Cantidad]]*Tabla4[[#This Row],[Costo ]] | P3: =Tabla4[[#This Row],[Subtotal]]+Tabla4[[#This Row],[Envío]] | Q3: OV0028020 | R3: MEL47172330443FMXDF01
A4: 28 de mayo de 2026 19:11 hs. | B4: Mercado Libre | D4: 28 de mayo de 2026 19:11 hs. | E4: 2000013224315483 | G4: María Guadalupe Esther Crispín | H4: =+_xlfn.XLOOKUP(Tabla4[[#This Row],[Título de la publicación]],ML!C:C,ML!A:A,1,0,1) | I4: Olnatura Just Colágeno Hidrolizado + Biotina 120 Gomitas Frutos Rojos | J4: =+_xlfn.XLOOKUP(Tabla4[[#This Row],[Dynamics]],ML!A:A,ML!B:B,1,0,1) | K4: 1 | M4: =+_xlfn.XLOOKUP(Tabla4[[#This Row],[Dynamics]],ML!A:A,ML!E:E,1,0,1) | N4: =Tabla4[[#This Row],[Cantidad]]*Tabla4[[#This Row],[Costo ]] | P4: =Tabla4[[#This Row],[Subtotal]]+Tabla4[[#This Row],[Envío]] | Q4: OV0028020 | R4: MEL47172134426FMXDF01
A5: 28 de mayo de 2026 18:51 hs. | B5: Mercado Libre | D5: 28 de mayo de 2026 18:51 hs. | E5: 2000013223965573 | G5: Esteban Lazo | H5: =+_xlfn.XLOOKUP(Tabla4[[#This Row],[Título de la publicación]],ML!C:C,ML!A:A,1,0,1) | I5: Colágeno Tipo 2 Premium. Sin Desnaturalizar 30 Cápsulas Olnatura Just Natural | J5: =+_xlfn.XLOOKUP(Tabla4[[#This Row],[Dynamics]],ML!A:A,ML!B:B,1,0,1) | K5: 2 | M5: =+_xlfn.XLOOKUP(Tabla4[[#This Row],[Dynamics]],ML!A:A,ML!E:E,1,0,1) | N5: =Tabla4[[#This Row],[Cantidad]]*Tabla4[[#This Row],[Costo ]] | P5: =Tabla4[[#This Row],[Subtotal]]+Tabla4[[#This Row],[Envío]] | Q5: OV0028020 | R5: MEL47171711373FMXDF01
A6: 28 de mayo de 2026 18:49 hs. | B6: Mercado Libre | D6: 28 de mayo de 2026 18:49 hs. | E6: 2000013223948613 | G6: Oliva Perez | H6: =+_xlfn.XLOOKUP(Tabla4[[#This Row],[Título de la publicación]],ML!C:C,ML!A:A,1,0,1) | I6: Colágeno Tipo 2 Premium. Sin Desnaturalizar 90 Cápsulas Olnatura Just Natural | J6: =+_xlfn.XLOOKUP(Tabla4[[#This Row],[Dynamics]],ML!A:A,ML!B:B,1,0,1) | K6: 1 | M6: =+_xlfn.XLOOKUP(Tabla4[[#This Row],[Dynamics]],ML!A:A,ML!E:E,1,0,1) | N6: =Tabla4[[#This Row],[Cantidad]]*Tabla4[[#This Row],[Costo ]] | P6: =Tabla4[[#This Row],[Subtotal]]+Tabla4[[#This Row],[Envío]] | Q6: OV0028020 | R6: MEL47171706021FMXDF01
A7: 28 de mayo de 2026 18:40 hs. | B7: Mercado Libre | D7: 28 de mayo de 2026 18:40 hs. | E7: 2000013223768681 | G7: Melissa Patricia Zavala | H7: =+_xlfn.XLOOKUP(Tabla4[[#This Row],[Título de la publicación]],ML!C:C,ML!A:A,1,0,1) | I7: Gomitas Probióticos Con Fibra Arándano Olnatura Just 120 Unid | J7: =+_xlfn.XLOOKUP(Tabla4[[#This Row],[Dynamics]],ML!A:A,ML!B:B,1,0,1) | K7: 1 | M7: =+_xlfn.XLOOKUP(Tabla4[[#This Row],[Dynamics]],ML!A:A,ML!E:E,1,0,1) | N7: =Tabla4[[#This Row],[Cantidad]]*Tabla4[[#This Row],[Costo ]] | P7: =Tabla4[[#This Row],[Subtotal]]+Tabla4[[#This Row],[Envío]] | Q7: OV0028020 | R7: MEL47171913796FMXDF01
A8: 28 de mayo de 2026 18:33 hs. | B8: Mercado Libre | D8: 28 de mayo de 2026 18:33 hs. | E8: 2000013220609499 | G8: Sergio Sanchez | H8: =+_xlfn.XLOOKUP(Tabla4[[#This Row],[Título de la publicación]],ML!C:C,ML!A:A,1,0,1) | I8: Olnatura Just Justfx Suplemento Glucosamina Condroitina Colágeno 120 Cápsulas Sin Sabor | J8: =+_xlfn.XLOOKUP(Tabla4[[#This Row],[Dynamics]],ML!A:A,ML!B:B,1,0,1) | K8: 3 | M8: =+_xlfn.XLOOKUP(Tabla4[[#This Row],[Dynamics]],ML!A:A,ML!E:E,1,0,1) | N8: =Tabla4[[#This Row],[Cantidad]]*Tabla4[[#This Row],[Costo ]] | P8: =Tabla4[[#This Row],[Subtotal]]+Tabla4[[#This Row],[Envío]] | Q8: OV0028020 | R8: MEL47171581699FMXDF01
A9: 28 de mayo de 2026 17:56 hs. | B9: Mercado Libre | D9: 28 de mayo de 2026 17:56 hs. | E9: 2000013223002303 | G9: Paulina Barron Guerrero | H9: =+_xlfn.XLOOKUP(Tabla4[[#This Row],[Título de la publicación]],ML!C:C,ML!A:A,1,0,1) | I9: Olnatura Justfx 90 Cápsulas De Glucosamina N/a | J9: =+_xlfn.XLOOKUP(Tabla4[[#This Row],[Dynamics]],ML!A:A,ML!B:B,1,0,1) | K9: 1 | M9: =+_xlfn.XLOOKUP(Tabla4[[#This Row],[Dynamics]],ML!A:A,ML!E:E,1,0,1) | N9: =Tabla4[[#This Row],[Cantidad]]*Tabla4[[#This Row],[Costo ]] | P9: =Tabla4[[#This Row],[Subtotal]]+Tabla4[[#This Row],[Envío]] | Q9: OV0028020 | R9: MEL47171313711FMXDF01
A10: 28 de mayo de 2026 17:26 hs. | B10: Mercado Libre | D10: 28 de mayo de 2026 17:26 hs. | E10: 2000013222523621 | G10: Cecilia Rincon | H10: =+_xlfn.XLOOKUP(Tabla4[[#This Row],[Título de la publicación]],ML!C:C,ML!A:A,1,0,1) | I10: Colágeno Tipo 2 Premium. Sin Desnaturalizar 90 Cápsulas Natural | J10: =+_xlfn.XLOOKUP(Tabla4[[#This Row],[Dynamics]],ML!A:A,ML!B:B,1,0,1) | K10: 1 | M10: =+_xlfn.XLOOKUP(Tabla4[[#This Row],[Dynamics]],ML!A:A,ML!E:E,1,0,1) | N10: =Tabla4[[#This Row],[Cantidad]]*Tabla4[[#This Row],[Costo ]] | P10: =Tabla4[[#This Row],[Subtotal]]+Tabla4[[#This Row],[Envío]] | Q10: OV0028020 | R10: MEL47171370396FMXDF01
A11: 28 de mayo de 2026 17:04 hs. | B11: Mercado Libre | D11: 28 de mayo de 2026 17:04 hs. | E11: 2000013222120117 | G11: Amparo Valdez | H11: =+_xlfn.XLOOKUP(Tabla4[[#This Row],[Título de la publicación]],ML!C:C,ML!A:A,1,0,1) | I11: Just Collagen 180 Tabletas | J11: =+_xlfn.XLOOKUP(Tabla4[[#This Row],[Dynamics]],ML!A:A,ML!B:B,1,0,1) | K11: 2 | M11: =+_xlfn.XLOOKUP(Tabla4[[#This Row],[Dynamics]],ML!A:A,ML!E:E,1,0,1) | N11: =Tabla4[[#This Row],[Cantidad]]*Tabla4[[#This Row],[Costo ]] | P11: =Tabla4[[#This Row],[Subtotal]]+Tabla4[[#This Row],[Envío]] | Q11: OV0028020 | R11: MEL47170933259FMXDF01
A12: 28 de mayo de 2026 16:32 hs. | B12: Mercado Libre | D12: 28 de mayo de 2026 16:32 hs. | E12: 2000013221578383 | G12: Alma Jenny Zubiate | H12: =+_xlfn.XLOOKUP(Tabla4[[#This Row],[Título de la publicación]],ML!C:C,ML!A:A,1,0,1) | I12: Olnatura Just Fx Glucosamina 120 Cápsulas Nutricional N/a | J12: =+_xlfn.XLOOKUP(Tabla4[[#This Row],[Dynamics]],ML!A:A,ML!B:B,1,0,1) | K12: 2 | M12: =+_xlfn.XLOOKUP(Tabla4[[#This Row],[Dynamics]],ML!A:A,ML!E:E,1,0,1) | N12: =Tabla4[[#This Row],[Cantidad]]*Tabla4[[#This Row],[Costo ]] | P12: =Tabla4[[#This Row],[Subtotal]]+Tabla4[[#This Row],[Envío]] | Q12: OV0028020 | R12: MEL47170705361FMXDF01
A13: 28 de mayo de 2026 16:02 hs. | B13: Mercado Libre | D13: 28 de mayo de 2026 16:02 hs. | E13: 2000013221130021 | G13: Leslie Abigail Borbon | H13: 503635000501 | I13: Colágeno Hidrolizado Premium Justcollagen 90 Tabletas | J13: JUSTCOLLAGEN 90 TABS | K13: 1 | M13: 241.38 | N13: =Tabla4[[#This Row],[Cantidad]]*Tabla4[[#This Row],[Costo ]] | P13: =Tabla4[[#This Row],[Subtotal]]+Tabla4[[#This Row],[Envío]] | Q13: OV0028020 | R13: MEL47170499999FMXDF01
A14: 28 de mayo de 2026 15:20 hs. | B14: Mercado Libre | D14: 28 de mayo de 2026 15:20 hs. | E14: 2000016657172978 | G14: Silvia Judith Reyes | H14: =+_xlfn.XLOOKUP(Tabla4[[#This Row],[Título de la publicación]],ML!C:C,ML!A:A,1,0,1) | I14: Just Collagen 180 Tabletas | J14: =+_xlfn.XLOOKUP(Tabla4[[#This Row],[Dynamics]],ML!A:A,ML!B:B,1,0,1) | K14: 1 | M14: =+_xlfn.XLOOKUP(Tabla4[[#This Row],[Dynamics]],ML!A:A,ML!E:E,1,0,1) | N14: =Tabla4[[#This Row],[Cantidad]]*Tabla4[[#This Row],[Costo ]] | P14: =Tabla4[[#This Row],[Subtotal]]+Tabla4[[#This Row],[Envío]] | Q14: OV0028020 | R14: MEL47170217079FMXDF01
A15: 28 de mayo de 2026 15:00 hs. | B15: Mercado Libre | D15: 28 de mayo de 2026 15:00 hs. | E15: 2000013220187561 | G15: Ivonne Bautista | H15: =+_xlfn.XLOOKUP(Tabla4[[#This Row],[Título de la publicación]],ML!C:C,ML!A:A,1,0,1) | I15: Olnatura Just Justfx Suplemento Glucosamina Condroitina Colágeno 120 Cápsulas Sin Sabor | J15: =+_xlfn.XLOOKUP(Tabla4[[#This Row],[Dynamics]],ML!A:A,ML!B:B,1,0,1) | K15: 1 | M15: =+_xlfn.XLOOKUP(Tabla4[[#This Row],[Dynamics]],ML!A:A,ML!E:E,1,0,1) | N15: =Tabla4[[#This Row],[Cantidad]]*Tabla4[[#This Row],[Costo ]] | P15: =Tabla4[[#This Row],[Subtotal]]+Tabla4[[#This Row],[Envío]] | Q15: OV0028020 | R15: MEL47170080063FMXDF01
A16: 28 de mayo de 2026 14:45 hs. | B16: Mercado Libre | D16: 28 de mayo de 2026 14:45 hs. | E16: 2000016656655078 | G16: Juan Angel Flores Santiago | H16: =+_xlfn.XLOOKUP(Tabla4[[#This Row],[Título de la publicación]],ML!C:C,ML!A:A,1,0,1) | I16: Just Collagen 180 Tabletas | J16: =+_xlfn.XLOOKUP(Tabla4[[#This Row],[Dynamics]],ML!A:A,ML!B:B,1,0,1) | K16: 1 | M16: =+_xlfn.XLOOKUP(Tabla4[[#This Row],[Dynamics]],ML!A:A,ML!E:E,1,0,1) | N16: =Tabla4[[#This Row],[Cantidad]]*Tabla4[[#This Row],[Costo ]] | P16: =Tabla4[[#This Row],[Subtotal]]+Tabla4[[#This Row],[Envío]] | Q16: OV0028020 | R16: MEL47170241332FMXDF01
A17: 28 de mayo de 2026 14:40 hs. | B17: Mercado Libre | D17: 28 de mayo de 2026 14:40 hs. | E17: 2000013219877093 | G17: Hisae Xanat Carbajal | H17: 503635000300 | I17: Olnatura Just Glucosamina Condroitina 410 Cápsulas Sabor N/a | J17: GLUCOSAMINA / CONDROITINA BOVINO 410 TAB | K17: 1 | M17: 758.62 | N17: =Tabla4[[#This Row],[Cantidad]]*Tabla4[[#This Row],[Costo ]] | P17: =Tabla4[[#This Row],[Subtotal]]+Tabla4[[#This Row],[Envío]] | Q17: OV0028020 | R17: MEL47169930945FMXDF01
A18: 28 de mayo de 2026 14:34 hs. | B18: Mercado Libre | D18: 28 de mayo de 2026 14:34 hs. | E18: 2000013219793151 | G18: Daniela Montes de Oca Méndez | H18: =+_xlfn.XLOOKUP(Tabla4[[#This Row],[Título de la publicación]],ML!C:C,ML!A:A,1,0,1) | I18: Olnatura Just Gomitas Biotina Arándano Sabor Frambuesa Vegano Sin Gluten 120 Uds | J18: =+_xlfn.XLOOKUP(Tabla4[[#This Row],[Dynamics]],ML!A:A,ML!B:B,1,0,1) | K18: 2 | M18: =+_xlfn.XLOOKUP(Tabla4[[#This Row],[Dynamics]],ML!A:A,ML!E:E,1,0,1) | N18: =Tabla4[[#This Row],[Cantidad]]*Tabla4[[#This Row],[Costo ]] | P18: =Tabla4[[#This Row],[Subtotal]]+Tabla4[[#This Row],[Envío]] | Q18: OV0028020 | R18: MEL47170166112FMXDF01
A19: 28 de mayo de 2026 14:16 hs. | B19: Mercado Libre | D19: 28 de mayo de 2026 14:16 hs. | E19: 2000013219476265 | G19: Gladis Galvez | H19: =+_xlfn.XLOOKUP(Tabla4[[#This Row],[Título de la publicación]],ML!C:C,ML!A:A,1,0,1) | I19: Olnatura Justfx 90 Cápsulas De Glucosamina N/a | J19: =+_xlfn.XLOOKUP(Tabla4[[#This Row],[Dynamics]],ML!A:A,ML!B:B,1,0,1) | K19: 3 | M19: =+_xlfn.XLOOKUP(Tabla4[[#This Row],[Dynamics]],ML!A:A,ML!E:E,1,0,1) | N19: =Tabla4[[#This Row],[Cantidad]]*Tabla4[[#This Row],[Costo ]] | P19: =Tabla4[[#This Row],[Subtotal]]+Tabla4[[#This Row],[Envío]] | Q19: OV0028020 | R19: MEL47169758557FMXDF01
A20: 28 de mayo de 2026 13:44 hs. | B20: Mercado Libre | D20: 28 de mayo de 2026 13:44 hs. | E20: 2000013218991453 | G20: Patricia Ramona Martinez | H20: =+_xlfn.XLOOKUP(Tabla4[[#This Row],[Título de la publicación]],ML!C:C,ML!A:A,1,0,1) | I20: Olnatura Glucosamina 240 Tabletas Boro Y Manganeso | J20: =+_xlfn.XLOOKUP(Tabla4[[#This Row],[Dynamics]],ML!A:A,ML!B:B,1,0,1) | K20: 1 | M20: =+_xlfn.XLOOKUP(Tabla4[[#This Row],[Dynamics]],ML!A:A,ML!E:E,1,0,1) | N20: =Tabla4[[#This Row],[Cantidad]]*Tabla4[[#This Row],[Costo ]] | P20: =Tabla4[[#This Row],[Subtotal]]+Tabla4[[#This Row],[Envío]] | Q20: OV0028020 | R20: MEL47169522595FMXDF01
A21: 28 de mayo de 2026 13:37 hs. | B21: Mercado Libre | D21: 28 de mayo de 2026 13:37 hs. | E21: 2000013218852733 | G21: Gilberto Pineda Yacotu | H21: =+_xlfn.XLOOKUP(Tabla4[[#This Row],[Título de la publicación]],ML!C:C,ML!A:A,1,0,1) | I21: Olnatura Justfx 90 Cápsulas De Glucosamina N/a | J21: =+_xlfn.XLOOKUP(Tabla4[[#This Row],[Dynamics]],ML!A:A,ML!B:B,1,0,1) | K21: 1 | M21: =+_xlfn.XLOOKUP(Tabla4[[#This Row],[Dynamics]],ML!A:A,ML!E:E,1,0,1) | N21: =Tabla4[[#This Row],[Cantidad]]*Tabla4[[#This Row],[Costo ]] | P21: =Tabla4[[#This Row],[Subtotal]]+Tabla4[[#This Row],[Envío]] | Q21: OV0028020 | R21: MEL47169738414FMXDF01
A22: 28 de mayo de 2026 12:45 hs. | B22: Mercado Libre | D22: 28 de mayo de 2026 12:45 hs. | E22: 2000013217989469 | G22: Jorge Alfredo Flores | H22: =+_xlfn.XLOOKUP(Tabla4[[#This Row],[Título de la publicación]],ML!C:C,ML!A:A,1,0,1) | I22: Just Collagen 180 Tabletas | J22: =+_xlfn.XLOOKUP(Tabla4[[#This Row],[Dynamics]],ML!A:A,ML!B:B,1,0,1) | K22: 2 | M22: =+_xlfn.XLOOKUP(Tabla4[[#This Row],[Dynamics]],ML!A:A,ML!E:E,1,0,1) | N22: =Tabla4[[#This Row],[Cantidad]]*Tabla4[[#This Row],[Costo ]] | P22: =Tabla4[[#This Row],[Subtotal]]+Tabla4[[#This Row],[Envío]] | Q22: OV0028020 | R22: MEL47169053815FMXDF01
A23: 28 de mayo de 2026 12:10 hs. | B23: Mercado Libre | D23: 28 de mayo de 2026 12:10 hs. | E23: 2000013217354333 | G23: Lidia Saavedra Espinoza | H23: =+_xlfn.XLOOKUP(Tabla4[[#This Row],[Título de la publicación]],ML!C:C,ML!A:A,1,0,1) | I23: Just Collagen 180 Tabletas | J23: =+_xlfn.XLOOKUP(Tabla4[[#This Row],[Dynamics]],ML!A:A,ML!B:B,1,0,1) | K23: 4 | M23: =+_xlfn.XLOOKUP(Tabla4[[#This Row],[Dynamics]],ML!A:A,ML!E:E,1,0,1) | N23: =Tabla4[[#This Row],[Cantidad]]*Tabla4[[#This Row],[Costo ]] | P23: =Tabla4[[#This Row],[Subtotal]]+Tabla4[[#This Row],[Envío]] | Q23: OV0028020 | R23: MEL47168771997FMXDF01
A24: 28 de mayo de 2026 11:56 hs. | B24: Mercado Libre | D24: 28 de mayo de 2026 11:56 hs. | E24: 2000013217112011 | G24: Martha Leticia Vargas Garcia | H24: =+_xlfn.XLOOKUP(Tabla4[[#This Row],[Título de la publicación]],ML!C:C,ML!A:A,1,0,1) | I24: Just Collagen 180 Tabletas | J24: =+_xlfn.XLOOKUP(Tabla4[[#This Row],[Dynamics]],ML!A:A,ML!B:B,1,0,1) | K24: 2 | M24: =+_xlfn.XLOOKUP(Tabla4[[#This Row],[Dynamics]],ML!A:A,ML!E:E,1,0,1) | N24: =Tabla4[[#This Row],[Cantidad]]*Tabla4[[#This Row],[Costo ]] | P24: =Tabla4[[#This Row],[Subtotal]]+Tabla4[[#This Row],[Envío]] | Q24: OV0028020 | R24: MEL47168657219FMXDF01
A25: 28 de mayo de 2026 09:45 hs. | B25: Mercado Libre | D25: 28 de mayo de 2026 09:45 hs. | E25: 2000013214727367 | G25: Rafael Lopez | H25: =+_xlfn.XLOOKUP(Tabla4[[#This Row],[Título de la publicación]],ML!C:C,ML!A:A,1,0,1) | I25: Olnatura Just Justfx Suplemento Glucosamina Condroitina Colágeno 120 Cápsulas Sin Sabor | J25: =+_xlfn.XLOOKUP(Tabla4[[#This Row],[Dynamics]],ML!A:A,ML!B:B,1,0,1) | K25: 1 | M25: =+_xlfn.XLOOKUP(Tabla4[[#This Row],[Dynamics]],ML!A:A,ML!E:E,1,0,1) | N25: =Tabla4[[#This Row],[Cantidad]]*Tabla4[[#This Row],[Costo ]] | P25: =Tabla4[[#This Row],[Subtotal]]+Tabla4[[#This Row],[Envío]] | Q25: OV0028020 | R25: MEL47167838140FMXDF01
A26: 28 de mayo de 2026 09:38 hs. | B26: Mercado Libre | D26: 28 de mayo de 2026 09:38 hs. | E26: 2000013214581527 | G26: Jose Luis Serrano Estevane | H26: 503635001700 | I26: Colágeno Hidrolizado Olnatura Just Collagen En Gomitas Con Sabor A Frutos Rojos | J26: JUSTCOLLAGEN 111 GOMAS | K26: 1 | M26: 362.07 | N26: =Tabla4[[#This Row],[Cantidad]]*Tabla4[[#This Row],[Costo ]] | P26: =Tabla4[[#This Row],[Subtotal]]+Tabla4[[#This Row],[Envío]] | Q26: OV0028020 | R26: MEL47167777540FMXDF01
A27: 28 de mayo de 2026 08:50 hs. | B27: Mercado Libre | D27: 28 de mayo de 2026 08:50 hs. | E27: 2000013213748157 | G27: Dora Cristina García Pérez | H27: =+_xlfn.XLOOKUP(Tabla4[[#This Row],[Título de la publicación]],ML!C:C,ML!A:A,1,0,1) | I27: Just For You Glucosamina Condroitina 240 Tabletas Original | J27: =+_xlfn.XLOOKUP(Tabla4[[#This Row],[Dynamics]],ML!A:A,ML!B:B,1,0,1) | K27: 2 | M27: =+_xlfn.XLOOKUP(Tabla4[[#This Row],[Dynamics]],ML!A:A,ML!E:E,1,0,1) | N27: =Tabla4[[#This Row],[Cantidad]]*Tabla4[[#This Row],[Costo ]] | P27: =Tabla4[[#This Row],[Subtotal]]+Tabla4[[#This Row],[Envío]] | Q27: OV0028020 | R27: MEL47167136773FMXDF01
A28: 28 de mayo de 2026 08:36 hs. | B28: Mercado Libre | D28: 28 de mayo de 2026 08:36 hs. | E28: 2000013213480501 | G28: Ernesto Martinez | H28: =+_xlfn.XLOOKUP(Tabla4[[#This Row],[Título de la publicación]],ML!C:C,ML!A:A,1,0,1) | I28: Colágeno Tipo 2 Premium. Sin Desnaturalizar 90 Cápsulas Olnatura Just Natural | J28: =+_xlfn.XLOOKUP(Tabla4[[#This Row],[Dynamics]],ML!A:A,ML!B:B,1,0,1) | K28: 2 | M28: =+_xlfn.XLOOKUP(Tabla4[[#This Row],[Dynamics]],ML!A:A,ML!E:E,1,0,1) | N28: =Tabla4[[#This Row],[Cantidad]]*Tabla4[[#This Row],[Costo ]] | P28: =Tabla4[[#This Row],[Subtotal]]+Tabla4[[#This Row],[Envío]] | Q28: OV0028020 | R28: MEL47167021647FMXDF01
A29: 28 de mayo de 2026 08:34 hs. | B29: Mercado Libre | D29: 28 de mayo de 2026 08:34 hs. | E29: 2000013213481153 | G29: ERIKA VALENCIA | H29: =+_xlfn.XLOOKUP(Tabla4[[#This Row],[Título de la publicación]],ML!C:C,ML!A:A,1,0,1) | I29: Isoflavonas Olnatura Just 90 Tabletas | J29: =+_xlfn.XLOOKUP(Tabla4[[#This Row],[Dynamics]],ML!A:A,ML!B:B,1,0,1) | K29: 1 | M29: =+_xlfn.XLOOKUP(Tabla4[[#This Row],[Dynamics]],ML!A:A,ML!E:E,1,0,1) | N29: =Tabla4[[#This Row],[Cantidad]]*Tabla4[[#This Row],[Costo ]] | P29: =Tabla4[[#This Row],[Subtotal]]+Tabla4[[#This Row],[Envío]] | Q29: OV0028020 | R29: MEL47167280818FMXDF01
A30: 28 de mayo de 2026 06:18 hs. | B30: Mercado Libre | D30: 28 de mayo de 2026 06:18 hs. | E30: 2000013211617045 | G30: Guadalupe pizano | H30: =+_xlfn.XLOOKUP(Tabla4[[#This Row],[Título de la publicación]],ML!C:C,ML!A:A,1,0,1) | I30: Olnatura Just Justfx Suplemento Glucosamina Condroitina Colágeno 120 Cápsulas Sin Sabor | J30: =+_xlfn.XLOOKUP(Tabla4[[#This Row],[Dynamics]],ML!A:A,ML!B:B,1,0,1) | K30: 1 | M30: =+_xlfn.XLOOKUP(Tabla4[[#This Row],[Dynamics]],ML!A:A,ML!E:E,1,0,1) | N30: =Tabla4[[#This Row],[Cantidad]]*Tabla4[[#This Row],[Costo ]] | P30: =Tabla4[[#This Row],[Subtotal]]+Tabla4[[#This Row],[Envío]] | Q30: OV0028020 | R30: MEL47166401160FMXDF01
A31: 28 de mayo de 2026 05:40 hs. | B31: Mercado Libre | D31: 28 de mayo de 2026 05:40 hs. | E31: 2000013211170011 | G31: Ana Maria Vega | H31: =+_xlfn.XLOOKUP(Tabla4[[#This Row],[Título de la publicación]],ML!C:C,ML!A:A,1,0,1) | I31: Olnatura Justfx 90 Cápsulas De Glucosamina N/a | J31: =+_xlfn.XLOOKUP(Tabla4[[#This Row],[Dynamics]],ML!A:A,ML!B:B,1,0,1) | K31: 1 | M31: =+_xlfn.XLOOKUP(Tabla4[[#This Row],[Dynamics]],ML!A:A,ML!E:E,1,0,1) | N31: =Tabla4[[#This Row],[Cantidad]]*Tabla4[[#This Row],[Costo ]] | P31: =Tabla4[[#This Row],[Subtotal]]+Tabla4[[#This Row],[Envío]] | Q31: OV0028020 | R31: MEL47165920891FMXDF01
A32: 28 de mayo de 2026 00:58 hs. | B32: Mercado Libre | D32: 28 de mayo de 2026 00:58 hs. | E32: 2000013210014493 | G32: Karla Paulina Anaya Gil | H32: =+_xlfn.XLOOKUP(Tabla4[[#This Row],[Título de la publicación]],ML!C:C,ML!A:A,1,0,1) | I32: Olnatura Just Justfx Suplemento Glucosamina Condroitina Colágeno 120 Cápsulas Sin Sabor | J32: =+_xlfn.XLOOKUP(Tabla4[[#This Row],[Dynamics]],ML!A:A,ML!B:B,1,0,1) | K32: 1 | M32: =+_xlfn.XLOOKUP(Tabla4[[#This Row],[Dynamics]],ML!A:A,ML!E:E,1,0,1) | N32: =Tabla4[[#This Row],[Cantidad]]*Tabla4[[#This Row],[Costo ]] | P32: =Tabla4[[#This Row],[Subtotal]]+Tabla4[[#This Row],[Envío]] | Q32: OV0028020 | R32: MEL47165334499FMXDF01
J33: PRODUCTO | K33: Suma
J34: JUSTFX 120 CAPS | K34: 9
J35: JUSTFX 90 CAPS | K35: 6
J36: COLAGENO TIPO II 90 CAPS | K36: 4
J37: GLUCOSAMINA / CONDROITINA TIBURON 240 TA | K37: 3
J38: COLAGENO TIPO II 30 CAPS | K38: 2
J39: JUSTCOLLAGEN 180 TABS | K39: 12
J40: JUSTCOLLAGEN 111 GOMAS | K40: 1
J41: GLUCOSAMINA / CONDROITINA BOVINO 410 TAB | K41: 1
J42: PROBIÓTICOS + FIBRA 120 GOMAS | K42: 1
J43: ISOFLAVONAS 90 TAB | K43: 2
J44: OMEGA 3 120 GOMAS | K44: 1
J45: COLÁGENO+BIOTINA 120 GOMAS | K45: 1
... J48: Total general | K48: 46

Sheet Hoja1

Sheet  20 % DESC ENE AMZ
A1: LISTADO DE PRECIOS E-COMM PROMOCIÓN ENERO | E1: -20% DESCUENTO ENERO
A2: PLATAFORMA | B2: PRODUCTO | C2: Precio de facturación | D2: Precio de venta | E2: Precio de facturación | F2: Precio de venta
A3: AMAZON PRIME | B3: COLAGENO TIPO II 90 CAPS | C3: =D3/1.16 | D3: 997 | E3: =F3/1.16 | F3: =D3*0.8
A4: AMAZON PRIME | B4: GLUCOSAMINA / CONDROITINA BOVINO 410 TAB | C4: =D4/1.16 | D4: 943 | E4: =F4/1.16 | F4: =D4*0.8
A5: AMAZON PRIME | B5: JUSTBIOH 110 GOMAS | C5: =D5/1.16 | D5: 443 | E5: =F5/1.16 | F5: =D5*0.8
A6: AMAZON PRIME | B6: JUSTBIOTICS 110 GOMAS | C6: =D6/1.16 | D6: 409 | E6: =F6/1.16 | F6: =D6*0.8
A7: AMAZON PRIME | B7: JUSTCOLLAGEN 111 GOMAS | C7: =D7/1.16 | D7: 390 | E7: =F7/1.16 | F7: =D7*0.8
A8: AMAZON PRIME | B8: JUSTOMEGA-3 110 GOMAS | C8: =D8/1.16 | D8: 390 | E8: =F8/1.16 | F8: =D8*0.8
A9: AMAZON VENDEDOR | B9: COLAGENO TIPO II 90 CAPS | C9: =D9/1.16 | D9: 1063 | E9: =F9/1.16 | F9: =D9*0.8
A10: AMAZON VENDEDOR | B10: GLUCOSAMINA / CONDROITINA BOVINO 410 TAB | C10: =D10/1.16 | D10: 943 | E10: =F10/1.16 | F10: =D10*0.8
A11: AMAZON VENDEDOR | B11: JUSTBIOTICS 110 GOMAS | C11: =D11/1.16 | D11: 409 | E11: =F11/1.16 | F11: =D11*0.8
A12: AMAZON VENDEDOR | B12: JUSTCOLLAGEN 111 GOMAS | C12: =D12/1.16 | D12: 390 | E12: =F12/1.16 | F12: =D12*0.8
A13: AMAZON VENDEDOR | B13: JUSTBIOH 110 GOMAS | C13: =D13/1.16 | D13: 443 | E13: =F13/1.16 | F13: =D13*0.8
A14: AMAZON VENDEDOR | B14: JUSTOMEGA-3 110 GOMAS | C14: =D14/1.16 | D14: 390 | E14: =F14/1.16 | F14: =D14*0.8

Sheet AMZ
A1: AMAZON
A3: CÓDIGO | B3: PRODUCTO | C3: TÍTULO PUBLICACIÓN | D3: Precio de facturación | E3: Precio de venta
A4: 503635000200 | B4: COLAGENO EN POLVO 210 GR | C4: Colágeno Hidrolizado Premium JustCollagen Polvo 210 gramos con Prebióticos FOS, Vitamina B3, Vitamina C, Zinc, Sin Grasas, Azúcar, Sodio y Lácteos, Sabor Fresa. | D4: 361.21 | E4: 366.0032
A5: 503635000606 | B5: COLAGENO TIPO II 90 CAPS | C5: Colágeno Tipo II Premium. Sin Desnaturalizar 90 Cápsulas + Vitamina E, Manganeso | D5: 939.651 | E5: 1063.0008
A6: 503635000606 | B6: COLAGENO TIPO II 90 CAPS | C6: Colágeno Tipo II Premium. Sin Desnaturalizar 90 Cápsulas + Vitamina E, Manganeso. | D6: 939.651
A7: 503635000606 | B7: COLAGENO TIPO II 90 CAPS | C7: Colágeno Tipo II Premium. Sin Desnaturalizar 90 Cápsulas + Vitamina E, Manganeso. | D7: 939.651
A8: 503635005100 | B8: COLAGENO TIPO II 30 CAPS | C8: Colágeno Tipo II Premium. Sin Desnaturalizar con Vitamina E y Manganeso 30 Cápsulas para - Olnatura Just | D8: 357.76 | E8: 529.0064
A9: 503635009800 | B9: COLAGENO TIPO II 30 CAPS | C9: Colï¿½geno Tipo II Premium. Sin Desnaturalizarcon Vitamina E y Manganeso 30 Cï¿½psulas para- Olnatura Just | D9: 357.76
A10: 503635009800 | B10: COLAGENO TIPO II 30 CAPS | C10: Colï¿½geno Tipo II Premium. Sin Desnaturalizar con Vitamina E y Manganeso 30 Cï¿½psulas para - Olnatura Just | D10: 357.76
A11: 503635009800 | B11: COLAGENO TIPO II 30 CAPS | C11: Colágeno Tipo II Premium. Sin Desnaturalizar con Vitamina E y Manganeso 30 Cápsulas para - Olnatura Just | D11: 357.76
A12: 503635000300 | B12: GLUCOSAMINA / CONDROITINA BOVINO 410 TAB | C12: Glucosamina Condroitina Premium, con Boro y Manganeso 410 tabletas SIN AZÚCAR, SIN SODIO y SIN GLUTEN | D12: 861.21 | E12: 942.9988
A13: 503635003900 | B13: JUSTCETRUX 180 | C13: JustCetrux 180 tabletas de Vitamina C + Vitamina A, Fibra Soluble, Zinc y Cobre, Sabor Manzana Verde. Suplemento Alimenticio. | D13: 180.17
A14: 503635002000 | B14: JUSTBIOTICS 110 GOMAS | C14: Probióticos Premium JustBiotics 110 gomitas con 100 millones de Lactobacilos Esporulados, Sabor Arándano. | D14: 361.21 | E14: 409.0044
A15: 503635696000 | B15: JUSTFIBRA 120 TABS | C15: JustFibra 120 tabletas de Fibra Dietética, Lactobacilos, Guayaba, Piña y Hierbabuena. Sin azúcar, sin grasas y sin sodio. | D15: 375
A16: 503635001700 | B16: JUSTCOLLAGEN 111 GOMAS | C16: Colágeno Hidrolizado Premium JustCollagen 111 gomitas, Sabor Frutos Rojos. | D16: 361.21 | E16: 390.0036
A17: 503635001700 | B17: JUSTCOLLAGEN 111 GOMAS | C17: Colï¿½geno Hidrolizado Premium JustCollagen 111 gomitas, Sabor Frutos Rojos. | D17: 361.21
A18: 503635001600 | B18: JUSTBIOH 110 GOMAS | C18: Biotina Premium + Arándano JustBio H 110 gomitas, Sabor Frambuesa. | D18: 361.21 | E18: 443.004
A19: 503635002600 | B19: JUSTCOLLAGEN 180 TABS | C19: Colágeno Hidrolizado Premium JustCollagen 180 Tabletas con Biotina, Calcio, Vitamina C, Vitamina E y Vitamina K | D19: 350 | E19: 395.0032
A20: 503635002600 | B20: JUSTCOLLAGEN 180 TABS | C20: Olnatura Just - Colágeno Hidrolizado Premium JustCollagen 180 Tabletas con Biotina, Calcio, Vitamina C, Vitamina E y Vitamina K. | D20: 350
A21: 503635002600 | B21: JUSTCOLLAGEN 180 TABS | C21: Olnatura Just - Colágeno Hidrolizado Premium JustCollagen 180 Tabletas con Biotina, Calcio, Vitamina C, Vitamina E y Vitamina K. | D21: 350
A22: 503635002600 | B22: JUSTCOLLAGEN 180 TABS | C22: Olnatura Just - Colï¿½geno Hidrolizado Premium JustCollagen 180 Tabletas con Biotina, Calcio, Vitamina C, Vitamina E y Vitamina K. | D22: 350
A23: 503635002600 | B23: JUSTCOLLAGEN 180 TABS | C23: Colágeno Hidrolizado Premium JustCollagen 180 Tabletas con Biotina, Calcio, Vitamina C, Vitamina E y Vitamina K. | D23: 350
A24: 503635000501 | B24: JUSTCOLLAGEN 90 TABS | C24: Colï¿½geno Hidrolizado Premium JustCollagen 90 Tabletas con Biotina, Calcio, Vitamina C, Vitamina E y Vitamina K. | D24: 241.38
A25: 503635000501 | B25: JUSTCOLLAGEN 90 TABS | C25: Colágeno Hidrolizado Premium JustCollagen 90 Tabletas con Biotina, Ca | D25: 241.38 | E25: 246.9988
A26: 503635000501 | B26: JUSTCOLLAGEN 90 TABS | C26: Colágeno Hidrolizado Premium JustCollagen 90 Tabletas con Biotina, Calcio, Vitamina C, Vitamina E y Vitamina K. | D26: 241.38
A27: 503635000705 | B27: JUSTFX 120 CAPS | C27: Glucosamina Condroitina Premium JustFx 120cápsulas con Ácido Hialurónico, ColágenoHidrolizado, Zinc y Boro. | D27: 550 | E27: 507.0012
A28: 503635000705 | B28: JUSTFX 120 CAPS | C28: Olnatura Just - Glucosamina Condroitina Premium JustFx 120 cï¿½psulas con ï¿½cido Hialurï¿½nico, Colï¿½geno Hidrolizado, Zinc y Boro. | D28: 550
A29: 503635000705 | B29: JUSTFX 120 CAPS | C29: Olnatura Just - Glucosamina CondroitinaPremium JustFx 120 cápsulas con ÁcidoHialurónico, Colágeno Hidrolizado, Zinc y Boro. | D29: 550
A30: 503635000705 | B30: JUSTFX 120 CAPS | C30: Olnatura Just - Glucosamina Condroitina Premium JustFx 120 cápsulas con Ácido Hialurónico, Colágeno Hidrolizado, Zinc y Boro. | D30: 550
A31: 503635000705 | B31: JUSTFX 120 CAPS | C31: Glucosamina Condroitina Premium JustFx 120 cápsulas con Ácido Hialurónico, Colágeno Hidrolizado, Zinc y Boro. | D31: 550
A32: 503635000900 | B32: JUSTFX 90 CAPS | C32: Glucosamina Condroitina Premium JustFx 90 cápsulas con Ácido Hialurónico, Colágeno Hidrolizado, Zinc y Boro. | D32: 375
A33: 503635000900 | B33: JUSTFX 90 CAPS | C33: Glucosamina Condroitina Premium JustFx 90 cï¿½psulas con ï¿½cido Hialurï¿½nico | D33: 375
A34: 503635000900 | B34: JUSTFX 90 CAPS | C34: Glucosamina Condroitina Premium JustFx 90cápsulas con Ácido Hialurónico, ColágenoHidrolizado, Zinc y Boro. | D34: 375
A35: 503635000900 | B35: JUSTFX 90 CAPS | C35: Glucosamina Condroitina Premium JustFx 90 cápsulas con Ácido Hialurónico, ColágenoHidrolizado, Zinc y Boro. | D35: 375 | E35: 390.0036
A36: 503635001800 | B36: JUSTOMEGA-3 110 GOMAS | C36: Omega 3, DHA y EPA (Ácidos Grasos Esenciales) Premium JustOmega 3 110 gomitas Sabor Mandarina. | D36: 361.21 | E36: 390.0036
A37: 503635004300 | B37: OMEGA 3 120 GOMAS | C37: Omega 3, DHA y EPA 120 gomitas de ácidos grasas escenciales sin grasas, sin sodio, sin gluten - Olnatura Just | D37: 272.41
A38: 503635004300 | B38: OMEGA 3 120 GOMAS | C38: Omega 3, DHA y EPA 120 gomitas de ï¿½cidos grasas escenciales sin grasas, sin sodio, sin gluten - Olnatura Just | D38: 272.41
A39: 503635001301 | B39: PROBIOTICOS GUMMYCARE 60 GOMAS | C39: Probióticos Premium SIN AZÚCAR, Gummy Care 60 gomitas de 120 millones de Lactobacilos Esporulados + Prebióticos, Sabor Mango-Yogurth. | D39: 343.1 | E39: 362.9988
A40: 503635005400 | B40: JUSTOLFOCUS 90 CAPS | C40: JustOlfocus 90 cápsulas de Glutamina, Fosfatidilserina, Zinc, Magnesio y 7 vitaminas, sin azúcar y sin sodio. | D40: 425
A41: 503635004500 | B41: COLÁGENO+BIOTINA 120 GOMAS | C41: Colágeno + Biotina 120 gomitas Olnatura Just, sabor frutos rojos | D41: 272.41
A42: 503635004500 | B42: COLÁGENO+BIOTINA 120 GOMAS | C42: Colï¿½geno + Biotina 120 gomitas Olnatura Just, sabor frutos rojos | D42: 272.41
A43: 503635695900 | B43: JUSTFIBRA 30 TABS | C43: JustFibra 30 tabletas de Fibra Dietética, Lactobacilos, Guayaba, Piña y Hierbabuena. Sin azúcar, sin grasas y sin sodio. | D43: 105.17
A44: 503635004600 | B44: BIOTINA 120 GOMAS | C44: Biotina + Arï¿½ndano 120 gomitas sin grasas, sin sodio, sin gluten - Olnatura Just | D44: 272.41
A45: 503635004600 | B45: BIOTINA 120 GOMAS | C45: Biotina + Arándano 120 gomitas sin grasas, sin sodio, sin gluten - Olnatura Just | D45: 272.41 | E45: 279.0032

Sheet ML
A1: MERCADO LIBRE
F2: Descuento
A3: CÓDIGO | B3: PRODUCTO | C3: TÍTULO PUBLICACIÓN | D3: Precio de venta normal | E3: Precio de facturación | F3: Precio de venta | G3: Precio de facturación2 | H3: Precio de facturación3
A4: 503635004600 | B4: BIOTINA 120 GOMAS | C4: Biotina + Arándano Olnatura Just 120 Gomitas Frambuesa | D4: 262.93 | E4: 262.93 | F4: =D4*0.95 | G4: =F4/1.16
A5: 503635004600 | B5: BIOTINA 120 GOMAS | C5: Olnatura Just Gomitas Biotina Arándano Sabor Frambuesa Vegano Sin Gluten 120 Uds | D5: 262.93 | E5: 262.93 | F5: =D5*0.95 | G5: =F5/1.16
A6: 503635004600 | B6: BIOTINA 120 GOMAS | C6: Biotina + Arándano Olnatura Just 120 Gomitas Sabor Frambuesa | D6: 262.93 | E6: 262.93 | F6: =D6*0.95 | G6: =F6/1.16
A7: 503635000200 | B7: COLAGENO EN POLVO 210 GR | C7: Colágeno Hidrolizado Premium Justcollagen Polvo | D7: 379 | E7: 344.83 | F7: =D7*0.95 | G7: =F7/1.16
A8: 503635000200 | B8: COLAGENO EN POLVO 210 GR | C8: Just Colágeno Hidrolizado Collagen 6000 En Polvo Sabor Fresa | D8: 379 | E8: 344.83 | F8: =D8*0.95 | G8: =F8/1.16
A9: 503635000200 | B9: COLAGENO EN POLVO 210 GR | C9: Colágeno Hidrolizado Premium Justcollagen Polvo Frutilla | D9: 379 | E9: 344.83 | F9: =D9*0.95 | G9: =F9/1.16
A10: 503635000200 | B10: COLAGENO EN POLVO 210 GR | C10: Just Colágeno Hidrolizado Collagen 6000 En Polvo Sabor Fresa Frutilla | D10: 379 | E10: 344.83 | F10: =D10*0.95 | G10: =F10/1.16
A11: 503635000200 | B11: COLAGENO EN POLVO 210 GR | C11: Just Collagen Polvo 210 Gramos Fresa | D11: 379 | E11: 344.83 | F11: =D11*0.95 | G11: =F11/1.16
A12: 503635000200 | B12: COLAGENO EN POLVO 210 GR | C12: Just Collagen Polvo 210 Gramos Frutilla | D12: 379 | E12: 344.83 | F12: =D12*0.95 | G12: =F12/1.16
A13: 503635009800 | B13: COLAGENO TIPO II 30 CAPS | C13: Colágeno Tipo 2 Premium. Sin Desnaturalizar 30 Cápsulas Olnatura Just Natural | E13: 405.17
A14: 503635009800 | B14: COLAGENO TIPO II 30 CAPS | C14: Colágeno Tipo 2 Premium. Sin Desnaturalizar 30 Cápsulas Olnatura Just | E14: 405.17
A15: 503635009800 | B15: COLAGENO TIPO II 30 CAPS | C15: Olnatura Just Colágeno Tipo Ii 30 Cápsulas Natural | E15: 405.17
A16: 503635009800 | B16: COLAGENO TIPO II 30 CAPS | C16: Olnatura Just Colágeno Tipo Ii 30 Cápsulas 13g Natural | E16: 405.17
A17: 503635009800 | B17: COLAGENO TIPO II 30 CAPS | C17: Colágeno Tipo 2 Sin Desnaturalizar + Vitamina E Y Manganeso Sabor Natural | D17: 547 | E17: 405.17 | F17: 0 | G17: 0
A18: 503635001010 | B18: COLAGENO TIPO II 90 CAPS | C18: Colágeno Tipo 2 Premium. Sin Desnaturalizar 90 Cápsulas | D18: 1063 | E18: 775.86 | F18: 0 | G18: 0
A19: 503635001010 | B19: COLAGENO TIPO II 90 CAPS | C19: Colágeno Tipo 2 Premium. Sin Desnaturalizar 90 Cápsulas Natural | D19: 1063 | E19: 775.86 | F19: 0 | G19: 0
A20: 503635001010 | B20: COLAGENO TIPO II 90 CAPS | C20: Colágeno Tipo 2 Premium. Sin Desnaturalizar 90 Cápsulas Olnatura Just | D20: 1063 | E20: 775.86 | F20: 0 | G20: 0
A21: 503635001010 | B21: COLAGENO TIPO II 90 CAPS | C21: Colágeno Tipo 2 Premium. Sin Desnaturalizar 90 Cápsulas Olnatura Just Natural | D21: 1063 | E21: 775.86 | F21: =D21*0.91 | G21: =F21/1.16
A22: 503635001010 | B22: COLAGENO TIPO II 90 CAPS | C22: Suplemento En Cápsulas Olnatura® Just For You Colágeno Tipo Ii Sin Desnaturalizar Uc Uc-ii Sabor Natural 90 Un | D22: 1063 | E22: 939.651 | F22: 0 | G22: 0
A23: 503635004500 | B23: COLÁGENO+BIOTINA 120 GOMAS | C23: Colágeno Hidrolizado + Biotina Olnatura Just 120 Gomas Frutos Rojos | D23: 288 | E23: 258.62 | F23: =D23*0.95 | G23: =F23/1.16
A24: 503635004500 | B24: COLÁGENO+BIOTINA 120 GOMAS | C24: Olnatura Just Colágeno Hidrolizado + Biotina 120 Gomitas Frutos Rojos | D24: 288 | E24: 258.62 | F24: =D24*0.95 | G24: =F24/1.16
A25: 503635004500 | B25: COLÁGENO+BIOTINA 120 GOMAS | C25: Colágeno Hidrolizado + Biotina Olnatura Just 120 Gomas | D25: 288 | E25: 258.62 | F25: =D25*0.95 | G25: =F25/1.16
A26: 503635004500 | B26: COLÁGENO+BIOTINA 120 GOMAS | C26: Colágeno Hidrolizado + Biotina Olnatura Just 120 Gomitas Sabor Frutos Rojos | D26: 288 | E26: 258.62 | F26: =D26*0.95 | G26: =F26/1.16
A27: 10 | B27: Dúo Pack Biotina 110 | C27: Biotina + Arándano Just Bio H 110 Gomitas 2 Piezas | D27: 841.71 | E27: KIT | F27: 0 | G27: 0
A28: 9 | B28: Dúo Pack Collagen 111 | C28: Colágeno Hidrolizado Just Collagen 111 Gomitas 2 Piezas | D28: 741.01 | E28: KIT | F28: 0 | G28: 0
A29: 8 | B29: Dúo Pack Glucosamina 240 | C29: Glucosamina Condroitina + Boro Y Manganeso 240 Tabletas 2 Pz | D29: 1134.31 | E29: KIT | F29: 0 | G29: 0
A30: 11 | B30: Dúo Pack Omega 3 110 | C30: Just Omega 3 110 Gomitas 2 Piezas | D30: 741.01 | E30: KIT | F30: 0 | G30: 0
A31: 503635000300 | B31: GLUCOSAMINA / CONDROITINA BOVINO 410 TAB | C31: Olnatura Just Glucosamina Condroitina 410 Cápsulas N/a | D31: 943 | E31: 758.62 | F31: 0 | G31: 0
A32: 503635000300 | B32: GLUCOSAMINA / CONDROITINA BOVINO 410 TAB | C32: Glucosamina Condroitina Boro Magnesio 410 Pz Just For You Sabor Sin Sabor | D32: 943 | E32: 758.62 | F32: 0 | G32: 0
A33: 503635000300 | B33: GLUCOSAMINA / CONDROITINA BOVINO 410 TAB | C33: Olnatura Just Glucosamina Condroitina 410 Cápsulas Sabor N/a | D33: 943 | E33: 758.62 | F33: 0 | G33: 0
A34: 503635000300 | B34: GLUCOSAMINA / CONDROITINA BOVINO 410 TAB | D34: 943 | E34: 758.62
A35: 503635000300 | B35: GLUCOSAMINA / CONDROITINA BOVINO 410 TAB | C35: Olnatura Just For You Glucosamina Cápsulas 410 Unid. N/a | D35: 943 | E35: 758.62
A36: 503635000100 | B36: GLUCOSAMINA / CONDROITINA TIBURON 240 TA | C36: Glucosamina 240 Tabletas Boro Y Manganeso Olnatura Just | D36: 597 | E36: 491.38 | F36: 0 | G36: 0
A37: 503635000100 | B37: GLUCOSAMINA / CONDROITINA TIBURON 240 TA | C37: Glucosamina 240 Tabletas Boro Y Manganeso Olnatura Just Original | D37: 597 | E37: 491.38 | F37: 0 | G37: 0
A38: 503635000100 | B38: GLUCOSAMINA / CONDROITINA TIBURON 240 TA | C38: Olnatura Glucosamina 240 Tabletas Boro Y Manganeso | D38: 597 | E38: 491.38
A39: 503635000100 | B39: GLUCOSAMINA / CONDROITINA TIBURON 240 TA | C39: Just For You Glucosamina Condroitina 240 Tabletas Original | D39: 597 | E39: 491.38
A40: 503635000100 | B40: GLUCOSAMINA / CONDROITINA TIBURON 240 TA | C40: Glucosamina Condroitina Just For You De Tiburón 240 Tabletas | D40: 597 | E40: 491.38 | F40: 0 | G40: 0
A41: 503635007000 | B41: JUSTBIOH 110 GOMAS BAJAS EN AZUCAR | C41: Olnatura Biotina Y Arándano 110 Gomas Reducidas En Azúcar Frutos Rojos | E41: 334.48
A42: 503635007000 | B42: JUSTBIOH 110 GOMAS BAJAS EN AZUCAR | C42: Biotina Gomas Olnatura Arándano Frutos Rojos 110 Pzas Salud Cabello | E42: 334.48
A43: 503635007000 | B43: JUSTBIOH 110 GOMAS BAJAS EN AZUCAR | C43: JUST BIOTINA + ARÁNDANO 110 GOMITAS (BAJAS EN AZÚCAR) | E43: 334.48
A44: 503635001600 | B44: JUSTBIOH 110 GOMAS | C44: Biotina Premium + Arándano Justbio H 110 Gomitas | D44: 443 | E44: 357.76 | F44: 0 | G44: 0
A45: 503635001600 | B45: JUSTBIOH 110 GOMAS | C45: Just Bio H Gomitas 110 Gomitas | D45: 443 | E45: 357.76 | F45: 0 | G45: 0
A46: 503635001600 | B46: JUSTBIOH 110 GOMAS | C46: Justbio H 110 Gomitas Biotina Más Arándano Olnatura | D46: 443 | E46: 357.76 | F46: 0 | G46: 0
A47: 503635001600 | B47: JUSTBIOH 110 GOMAS | C47: Olnatura Justbio H Gomitas 110 Unid Biotina 726g | D47: 443 | E47: 357.76 | F47: 0 | G47: 0
A48: 503635001600 | B48: JUSTBIOH 110 GOMAS | C48: Justbio H 110 Gomitas Biotina Más Arándano Olnatura Sabor Frambuesa | D48: 443 | E48: 357.76
A49: 503635002000 | B49: JUSTBIOTICS 110 GOMAS | C49: Probioticos Lactobacilos Arandano 110 Gomitas Olnatura Just | D49: 409 | E49: 357.76 | F49: =D49*0.95 | G49: =F49/1.16
A50: 503635002000 | B50: JUSTBIOTICS 110 GOMAS | C50: Just Gomitas Probioticos Lactobacilos 726 Ml 110 Unid. | D50: 409 | E50: 357.76 | F50: =D50*0.95 | G50: =F50/1.16
A51: 503635002000 | B51: JUSTBIOTICS 110 GOMAS | C51: Just Probioticos Lactobacilos Arandano 110 Gomitas | D51: 409 | E51: 357.76 | F51: =D51*0.95 | G51: =F51/1.16
A52: 503635002000 | B52: JUSTBIOTICS 110 GOMAS | C52: Probióticos Premium Justbiotics 110 Gomitas | D52: 409 | E52: 357.76 | F52: =D52*0.95 | G52: =F52/1.16
A53: 503635007200 | B53: JUST PROBIOTICOS 110 BAJAS EN AZUCAR | C53: JUST PROBIÓTICOS + FIBRA 110 GOMITAS (BAJAS EN AZÚCAR) | E53: 334.48
A54: 503635007200 | B54: JUST PROBIOTICOS 110 BAJAS EN AZUCAR | C54: Probióticos + Fibra Soluble, 110 Gomas Reducidas En Azúcar Frutos Rojos | E54: 334.48
A55: 503635004200 | B55: JUSTCALOSTRO 30 CAPS | C55: Calostro Bovino + Zinc Justcalostro 30 Cápsulas | E55: 0
A56: 503635004200 | B56: JUSTCALOSTRO 30 CAPS | C56: Calostro Bovino + Zinc Justcalostro 30 Cápsulas | D56: 189 | E56: 0 | F56: 0 | G56: 0
A57: 503635004200 | B57: JUSTCALOSTRO 30 CAPS | C57: Calostro Bovino + Zinc Justcalostro 30 Cápsulas Sabor Sin Sabor | D57: 189 | E57: 0
B58: JUSTCETRUX 180 | C58: Just Cetrux Vitamina C 180 Tabletas 1450mg C/u Olnatura | D58: 199 | E58: 168.1 | F58: =D58*0.95 | G58: =F58/1.16
B59: JUSTCETRUX 180 | C59: Vitamina C + Zinc Justcetrux 180 Tabletas | D59: 199 | E59: 168.1 | F59: =D59*0.95 | G59: =F59/1.16
A60: 503635003700 | B60: JUSTCETRUX 60 | C60: Vitamina C + Zinc + Probioticos Fos Justcetrux 60 Tabletas | D60: 97 | E60: 109.05 | F60: 0 | G60: 0
A61: 503635003700 | B61: JUSTCETRUX 60 | C61: Vitamina C + Zinc + Probioticos Fos Justcetrux 60 Tabletas Sabor Manzana Verde | D61: 97 | E61: 109.05 | F61: 0 | G61: 0
A62: 503635003700 | B62: JUSTCETRUX 60 | C62: Vitamina C + Zinc + Probioticos Fos Justcetrux 60 Tabletas Manzana Verde | E62: 109.05
A63: 503635001700 | B63: JUSTCOLLAGEN 111 GOMAS | C63: Colágeno Hidrolizado Premium Justcollagen 111 Gomitas | D63: 390 | E63: 362.07 | F63: 0 | G63: 0
A64: 503635001700 | B64: JUSTCOLLAGEN 111 GOMAS | C64: Colágeno Hidrolizado Premium Justcollagen 111 Gomitas Frutos Rojos | D64: 390 | E64: 362.07 | F64: 0 | G64: 0
A65: 503635001700 | B65: JUSTCOLLAGEN 111 GOMAS | C65: Just Collagen Gomitas 111 Gomitas | D65: 390 | E65: 362.07 | F65: 0 | G65: 0
A66: 503635006900 | B66: JUSTCOLLAGEN 111 GOMAS BAJA EN AZUCAR | C66: Colágeno Hidrolizado + Biotina 111 Gomas Bajas En Azucar Frutos Rojos | E66: 334.48
A67: 503635006900 | B67: JUSTCOLLAGEN 111 GOMAS BAJA EN AZUCAR | C67: Gomitas Colágeno Hidrolizado Biotina Olnatura 110 Frutos Rojos | E67: 334.48
A68: 503635006900 | B68: JUSTCOLLAGEN 111 GOMAS BAJA EN AZUCAR | C68: Gomitas Colágeno Hidrolizado Biotina Olnatura 111 Frutos Rojos | E68: 334.48
A69: 503635006900 | B69: JUSTCOLLAGEN 111 GOMAS BAJA EN AZUCAR | C69: JUST COLÁGENO H + BIOTINA 111 GOMITAS (BAJAS EN AZÚCAR) | E69: 334.48
A70: 503635001700 | B70: JUSTCOLLAGEN 111 GOMAS | C70: Just Collagen Gomitas 111 Gomitas Sabor Frutos Rojos | E70: 362.07
A71: 503635002600 | B71: JUSTCOLLAGEN 180 TABS | C71: Colágeno Hidrolizado Premium Justcollagen 180 Tabletas | D71: 395 | E71: 297.41 | F71: 0 | G71: 0
A72: 503635002600 | B72: JUSTCOLLAGEN 180 TABS | C72: Just Collagen 180 Tabletas | D72: 395 | E72: 297.41 | F72: =D72*0.87 | G72: =F72/1.16
A73: 503635000501 | B73: JUSTCOLLAGEN 90 TABS | C73: Colágeno Hidrolizado Premium Justcollagen 90 Tabletas | D73: 255.2 | E73: 241.38 | F73: 0 | G73: 0
A74: 503635000501 | B74: JUSTCOLLAGEN 90 TABS | C74: Just Collagen 90 Tabletas | D74: 255.2 | E74: 241.38 | F74: 0 | G74: 0
A75: 503635695900 | B75: JUSTFIBRA 30 TABS | C75: Olnatura Just Fibra 30 Tabletas Nutricional Fos Guayaba Sin Sabor | E75: 112.07
A76: 503635695900 | B76: JUSTFIBRA 30 TABS | C76: Suplemento En Tabletas Olnatura Just Suplemento Alimenticio Justfibra Fibra Dietética 30 Un Sin Sabor | E76: 112.07
A77: 503635696000 | B77: JUSTFIBRA120 | C77: Olnatura Just Fibra 120 Tabletas Nutricionales | D77: 375 | E77: 375
A78: 503635696000 | B78: JUSTFIBRA120 | C78: Suplemento En Tabletas Olnatura Just Suplemento Alimenticio Justfibra 120 Fibra Dietética 120 Un Sin Sabor | D78: 375 | E78: 375
A79: 503635696000 | B79: JUSTFIBRA120 | C79: Suplemento En Tabletas Olnatura Just Suplemento Alimenticio Justfibra 120 Fibra Dietética 120 Un | D79: 375 | E79: 375
A80: 503635005600 | B80: Just fx 120+% cápsulas | C80: Just fx 120+% cápsulas | D80: 507 | E80: 431.03 | F80: =D80*0.91 | G80: =F80/1.16
A81: 503635000705 | B81: JUSTFX 120 CAPS | C81: Glucosamina Condroitina Premium Justfx 120 Cápsulas | D81: 507 | E81: 431.03 | F81: =D81*0.91 | G81: =F81/1.16
A82: 503635000705 | B82: JUSTFX 120 CAPS | C82: Suplemento Olnatura Just Justfx Glucosamina Condroitina Con Ácido Hialurónico Y Colágeno 120 Cápsulas Sin Sabor | D82: 507 | E82: 431.03 | F82: =D82*0.91 | G82: =F82/1.16
A83: 503635000705 | B83: JUSTFX 120 CAPS | C83: Suplemento En Cápsulas Olnatura Just Justfx Sulfato De Glucosamina En Pote De 66.92g 120 Un | D83: 507 | E83: 431.03 | F83: =D83*0.91 | G83: =F83/1.16
A84: 503635000705 | B84: JUSTFX 120 CAPS | C84: Olnatura Just Justfx Suplemento Glucosamina Condroitina Colágeno 120 Cápsulas Sin Sabor | D84: 507 | E84: 431.03 | F84: =D84*0.91 | G84: =F84/1.16
A85: 503635000705 | B85: JUSTFX 120 CAPS | C85: Suplemento Olnatura Just Justfx Glucosamina Condroitina Con Ácido Hialurónico Y Colágeno 120 Cápsulas | D85: 507 | E85: 431.03 | F85: =D85*0.91 | G85: =F85/1.16
A86: 503635000705 | B86: JUSTFX 120 CAPS | C86: Olnatura Just Fx Glucosamina 120 Cápsulas Nutricional | D86: 507 | E86: 431.03 | F86: =D86*0.91 | G86: =F86/1.16
A87: 503635000705 | B87: JUSTFX 120 CAPS | C87: Olnatura Just Fx Glucosamina 120 Cápsulas Nutricional N/a | D87: 507 | E87: 431.03 | F87: =D87*0.91 | G87: =F87/1.16
A88: 503635000705 | B88: JUSTFX 120 CAPS | C88: Olnatura Just Fx 120 Cápsulas De Glucosamina N/a | D88: 507 | E88: 431.03 | F88: =D88*0.91 | G88: =F88/1.16
A89: 503635000705 | B89: JUSTFX 120 CAPS | C89: Suplemento En Cápsulas Olnatura Just Justfx Sulfato De Glucosamina En Pote De 66.92g 120 Un | D89: 507 | E89: 431.03
A90: 503635000705 | B90: JUSTFX 120 CAPS | C90: Olnatura Just Fx Glucosamina 120 Cápsulas Nutricional Sin Sabor | D90: 507 | E90: 431.03
A91: 503635000900 | B91: JUSTFX 90 CAPS | C91: Glucosamina Condroitina Premium Justfx 90 Cápsulas | D91: 399 | E91: 370.69 | F91: =D91*0.91 | G91: =F91/1.16
A92: 503635000900 | B92: JUSTFX 90 CAPS | C92: Justfx 90 Cápsulas De Glucosamina Olnatura | D92: 399 | E92: 375 | F92: =D92*0.91 | G92: =F92/1.16
A93: 503635000900 | B93: JUSTFX 90 CAPS | C93: Olnatura Justfx 90 Cápsulas De Glucosamina N/a | D93: 399 | E93: 375 | F93: =D93*0.91 | G93: =F93/1.16
A94: 503635000900 | B94: JUSTFX 90 CAPS | C94: Olnatura Just Justfx Glucosamina 90 Cápsulas 50.19g N/a | D94: 399 | E94: 375 | F94: =D94*0.91 | G94: =F94/1.16
A95: 503635000900 | B95: JUSTFX 90 CAPS | C95: Suplemento En Cápsulas Olnatura Just Justfx Sulfato De Glucosamina En Pote De 50.19g 90 un | D95: 399 | E95: 375 | F95: 0 | G95: 0
A96: 503635000900 | B96: JUSTFX 90 CAPS | C96: Suplemento Olnatura Just Sulfato De Glucosamina De 0.557g X 90 Un - Cápsula | D96: 399 | E96: 375 | F96: 0 | G96: 0
A97: 503635000900 | B97: JUSTFX 90 CAPS | C97: Suplemento En Cápsula Olnatura Just Sulfato De Glucosamina X 557mg | D97: 399 | E97: 375 | F97: 0 | G97: 0
A98: 503635000900 | B98: JUSTFX 90 CAPS | C98: Suplemento En Cápsulas Olnatura Just Justfx Sulfato De Glucosamina En Pote De 50.19g 90 Un | D98: 399 | E98: 375
A99: 503635000900 | B99: JUSTFX 90 CAPS | C99: Suplemento Olnatura Just Justfx De 0.557g X 90 Un - Cápsula | D99: 399 | E99: 375
A100: 503635005900 | B100: JUSTOLFOCUS 90 CAPS | C100: Olnatura Just Olfocus 90 Cápsulas L-glutamina + Vitaminas | D100: 493 | E100: 344.83 | F100: =D100*0.95 | G100: =F100/1.16
...

Sheet JT
A1: PÁGINA JUST
A3: CÓDIGO | B3: PRODUCTO | C3: TÍTULO PUBLICACIÓN | D3: Precio de facturación | E3: Precio de venta
A4: 503635000200 | B4: COLAGENO EN POLVO 210 GR | C4: JustCollagen Polvo 210 gr de Colágeno Hidrolizado + Prebióticos | D4: 344.83 | E4: 348.9976
A5: 503635000200 | B5: COLAGENO EN POLVO 210 GR | C5: JustCollagen Polvo 210 gr de Colágeno Hidrolizado + Prebióticos Just Collagen Polvo 210 Gramos | D5: 314.655
A6: 503635000200 | B6: COLAGENO EN POLVO 210 GR | C6: Colágeno Hidrolizado en Polvo 210 gramos SIN AZÚCAR Just Collagen Polvo 210 Gramos | D6: 314.655
A7: 503635000606 | B7: COLAGENO TIPO II 90 CAPS | C7: Colágeno Tipo II + Vitamina E y Manganeso 90 Cápsulas | D7: 861.21 | E7: 1058.9988
A8: 503635000606 | B8: COLAGENO TIPO II 90 CAPS | C8: Colágeno Tipo II + Vitamina E y Manganeso 90 Cápsulas Colágeno Tipo II 90 Cápsulas | D8: 775.86
A9: 503635000606 | B9: COLAGENO TIPO II 90 CAPS | C9: Colágeno Tipo 2 + Vitamina E y Manganeso 90 Cápsulas Colágeno Tipo II 90 Cápsulas | D9: 861.21
A10: 503635009800 | B10: COLAGENO TIPO II 30 CAPS | C10: Colágeno Tipo II + Vitamina E y Manganeso 30 Cápsulas | D10: 327.585 | E10: 508.9964
A11: 503635000400 | B11: JUSTCOLLAGEN 30 TABS | C11: Colágeno Hidrolizado + Biotina - Nutrilínea 30 Tabletas 1800 mg Just Collagen 30 Tabletas | D11: 85.345
B12: GLUCOSAMINA / CONDROITINA TIBURON 160 TA | C12: Glucosamina Condroitina de tiburón + Boro y Manganeso 160 Tabletas | D12: 0 | E12: 498.9972
A13: 503635000100 | B13: GLUCOSAMINA / CONDROITINA TIBURON 240 TA | C13: Glucosamina Condroitina de tiburón + Boro y Manganeso 240 Tabletas | D13: 491.38 | E13: 594.9988
A14: 503635000300 | B14: GLUCOSAMINA / CONDROITINA BOVINO 410 TAB | C14: Glucosamina Condroitina + Boro y Manganeso 410 Tabletas | D14: 758.62 | E14: 940
A15: 503635000300 | B15: GLUCOSAMINA / CONDROITINA BOVINO 410 TAB | C15: Glucosamina Condroitina + Boro y Manganeso 410 Tabletas Glucosamina 410 Tabs | D15: 792.24
A16: 503635001600 | B16: JUSTBIOH 110 GOMAS | C16: JustBio H 110 Gomitas de Biotina + Arándano | D16: 331.9 | E16: 440.9972
A17: 503635002000 | B17: JUSTBIOTICS 110 GOMAS | C17: JustBiotics 110 Gomitas de Probióticos con 100 millones de Lactobacilos | D17: 331.9 | E17: 406.9976
A18: 503635002000 | B18: JUSTBIOTICS 110 GOMAS | C18: 110 Gomitas de Probióticos con 110 millones de Lactobacilos Just Biotics Gomitas 110 Gomitas | D18: 331.9
A19: 503635002000 | B19: JUSTBIOTICS 110 GOMAS | C19: JustBiotics 110 Gomitas de Probióticos con 100 millones de Lactobacilos Just Biotics Gomitas 110 Gomitas | D19: 331.9
A20: 503635003700 | B20: JUSTCETRUX 60 | C20: JustCetrux 60 Tabletas de Vitamina C + Vitamina A y Zinc | D20: 94.83 | E20: 88.9952
A21: 503635003900 | B21: JUSTCETRUX 180 | C21: JustCetrux 180 Tabletas de Vitamina C + Vitamina A y Zinc Justcetrux 180 Tabletas | D21: 163.79
A22: 503635003900 | B22: JUSTCETRUX 180 | C22: Vitamina C Just Cetrux + Vitamina A y Zinc 180 Tabletas Justcetrux 180 Tabletas | D22: 163.79
A23: 503635001700 | B23: JUSTCOLLAGEN 111 GOMAS | C23: JustCollagen 111 Gomitas de Colágeno Hidrolizado 1800 mg | D23: 362.07 | E23: 389
A24: 503635002600 | B24: JUSTCOLLAGEN 180 TABS | C24: JustCollagen 180 Tabletas de Colágeno Hidrolizado 1800 mg + Biotina Just Collagen 180 Tabletas | D24: 297.41 | E24: 395.0032
A25: 503635000501 | B25: JUSTCOLLAGEN 90 TABS | C25: JustCollagen 90 Tabletas de Colágeno Hidrolizado 1800 mg + Biotina | D25: 241.38 | E25: 220
A26: 503635000501 | B26: JUSTCOLLAGEN 90 TABS | C26: JustCollagen 90 Tabletas de Colágeno Hidrolizado 1800 mg + Biotina Just Collagen 90 Tabletas | D26: 211.21
A27: 503635000705 | B27: JUSTFX 120 CAPS | C27: JustFx 120 Cápsulas de Glucosamina Condroitina + Colágeno y Zinc | D27: 431.03 | E27: 505
A28: 503635000705 | B28: JUSTFX 120 CAPS | C28: JustFx 120 Cápsulas de Glucosamina Condroitina + Colágeno y Zinc Just Fx 120 Cápsulas | D28: 405.17
A29: 503635000900 | B29: JUSTFX 90 CAPS | C29: JustFx 90 Cápsulas de Glucosamina Condroitina + Colágeno y Zinc | D29: 338.79 | E29: 368.996
A30: 503635000900 | B30: JUSTFX 90 CAPS | C30: Glucosamina Condroitina JustFx + Colágeno y Zinc 90 Cápsulas Just Fx 90 Cápsulas | D30: 370.69
A31: 503635000900 | B31: JUSTFX 90 CAPS | C31: JustFx 90 Cápsulas de Glucosamina Condroitina + Colágeno y Zinc Just Fx 90 Cápsulas | D31: 338.79
A32: 503635004200 | B32: JUSTCALOSTRO 30 CAPS | C32: JustCalostro 30 Cápsulas de Calostro Bovino + Zinc y Vitamina A | D32: 0 | E32: 167
A33: 503635004200 | B33: JUSTCALOSTRO 30 CAPS | C33: JustCalostro 30 Cápsulas de Calostro Bovino + Zinc y Vitamina A | D33: 0
A34: 503635001800 | B34: JUSTOMEGA-3 110 GOMAS | C34: JustOmega 3 110 Gomitas de Omega 3 con ácidos grasos EPA y DHA | D34: 331.9 | E34: 390.0036
A35: 503635001800 | B35: JUSTOMEGA-3 110 GOMAS | C35: JustOmega 3 110 Gomitas de Omega 3 con ácidos grasos EPA y DHA Just Omega 3 Gomitas 110 Gomitas | D35: 331.9
A36: 503635005400 | B36: JUSTOLFOCUS 90 CAPS | C36: JustOlfocus 90 Cápsulas de Glutamina + 7 vitaminas | D36: 344.83
A37: 503635005400 | B37: JUSTOLFOCUS 90 CAPS | C37: Glutamina JustOlfocus 90 Cápsulas | D37: 344.83
A38: 503635001301 | B38: PROBIOTICOS GUMMYCARE 60 GOMAS | C38: Gummy Care 60 Gomitas de Probióticos SIN AZÚCAR | D38: 344.83 | E38: 348.9976
A39: 503635001301 | B39: PROBIOTICOS GUMMYCARE 60 GOMAS | C39: Gummy Care 60 Gomitas de Probióticos SIN AZÚCAR Gummy Care Probióticos 60 gomitas | D39: 344.83
A40: 503635004500 | B40: COLÁGENO+BIOTINA 120 GOMAS | C40: Colágeno Hidrolizado + Biotina 120 gomitas | D40: 344.83 | E40: 266.9972
A41: 503635004500 | B41: COLÁGENO+BIOTINA 120 GOMAS | C41: 120 Gomitas Colágeno Hidrolizado + Biotina | D41: 344.83
A42: 503635004500 | B42: COLÁGENO+BIOTINA 120 GOMAS | C42: ¡NUEVO! Colágeno Hidrolizado + Biotina 120 gomitas | D42: 258.62
A43: 503635004400 | B43: PROBIÓTICOS + FIBRA 120 GOMAS | C43: Probióticos + Fibra 120 Gomitas con 100 millones de Lactobacilos esporulados OUTLET | D43: 258.62 | E43: 266.9972
A44: 503635004400 | B44: PROBIÓTICOS + FIBRA 120 GOMAS | C44: ¡NUEVO! Probióticos + Fibra Soluble 120 Gomitas | D44: 237.07
A45: 503635004300 | B45: OMEGA 3 120 GOMAS | C45: Omega 3 ácidos grasos EPA y DHA 120 Gomitas OUTLET | D45: 267.24 | E45: 266.9972
A46: 503635004300 | B46: OMEGA 3 120 GOMAS | D46: 237.07
A47: 503635004600 | B47: BIOTINA 120 GOMAS | C47: Biotina + Arándano 120 gomitas OUTLET | D47: 258.62 | E47: 266.9972
A48: 1 | B48: PACK JUSTFX 120 | C48: Pack 2 JustFx 120 Cápsulas de Glucosamina Condroitina + Colágeno y Zinc | D48: 435.34483
A49: 503635695900 | B49: JUSTFIBRA 30 TABS | C49: JUSTFIBRA 30 TABS | D49: 112.07
A50: 503635696000 | B50: JUSTFIBRA 120 TABS | C50: Just Fibra 120 Tabletas De Fos + Guayaba, Piña Y Hierbabuena. | D50: 341.38
A51: 503635696000 | B51: JUSTFIBRA 120 TABS | C51: Tabletas Guayaba, Piña e Hierbabuena Just Fibra de 120 | D51: 341.38
A52: 503635696000 | B52: JUSTFIBRA 120 TABS | C52: Just Fibra 120 Tabletas De Fos + Guayaba, Piña Y Hierbabuena | D52: 341.38
A53: 503635005100 | B53: COLAGENO TIPO II 30 CAPS | C53: COLAGENO TIPO II 30 CAPS | D53: 405.17
A54: 503635001020 | B54: JUST ISOFLAVONAS | C54: JUST ISOFLAVONAS | D54: 515.52

Sheet MUESTRAS
B3: PRODUCTO USO EXTERNO | G3: PRODUCTO USO INTERNO
B4: Piezas | C4: Producto | D4: Precio Fact. | E4: Total | G4: Piezas | H4: Producto | I4: Precio Fact. | J4: Total
B5: 1 | C5: JUSTCOLLAGEN POLVO | D5: 216.53 | E5: =D5*B5 | G5: 1 | H5: JUSTCOLLAGEN POLVO (C.Caducidad) | I5: 73.9904 | J5: =I5*G5
B6: 1 | C6: JUSTCOLLAGEN 90 | D6: 152.5 | E6: =D6*B6 | G6: 1 | H6: OMEGA 3 120 GOMAS (C.Caducidad) | I6: 60.8609 | J6: =I6*G6
B7: 1 | C7: JUSTCOLLAGEN 111 GOMAS | D7: 260 | E7: =D7*B7 | G7: 1 | H7: BIOTINA 120 GOMAS (C.Caducidad) | I7: 66.2985 | J7: =I7*G7
B8: 1 | C8: COLÁGENO + BIOTINA 120 GOMAS | D8: 167 | E8: =D8*B8 | G8: 1 | H8: PROBIÓTICOS 120 GOMAS (C.Caducidad) | I8: 68.0533 | J8: =I8*G8
B9: 1 | C9: PROBIÓTICOS 110 GOMAS | D9: 271 | E9: =D9*B9 | G9: 1 | H9: JUSTCETRUX 60 TABS (C.Caducidad) | I9: 23.0997 | J9: =I9*G9
B10: 1 | C10: BIOTINA 110 GOMAS | D10: 295.6 | E10: =D10*B10 | G10: 1 | H10: JUSTCOLLAGEN 111 GOMAS | I10: 88.2762 | J10: =I10*G10
B11: 1 | C11: BIOTINA 120 GOMAS | D11: 167 | E11: =D11*B11
B12: 1 | C12: PROBIÓTICOS 120 GOMAS | D12: 167 | E12: =D12*B12
B13: 1 | C13: GLUCOSAMINA 160 | D13: 334.18 | E13: =D13*B13
B14: 1 | C14: OMEGA 120 GOMAS | D14: 167 | E14: =D14*B14
B15: 1 | C15: JUSTCOLLAGEN 180 TABLETAS | D15: 263.9154 | E15: =D15*B15
B16: 1 | C16: JUSTFX 120 CÁPSULAS | D16: 338.2455 | E16: =D16*B16
B17: 1 | C17: OMEGA 3 110 GOMAS | D17: 260 | E17: =D17*B17
B18: 1 | C18: GLUCOSAMINA 410 TABLETAS | D18: 629.63635 | E18: =D18*B18
B19: 1 | C19: GUMMYCARE 60 GOMAS | D19: 215 | E19: =D19*B19
B20: 1 | C20: OMEGA 3 120 GOMAS (C.Caducidad ENE-24) | D20: 119.17241 | E20: =D20*B20
B21: 1 | C21: JUSTCOLLAGEN 90 | D21: 152.5 | E21: =D21*B21
B22: 1 | C22: JUSTFX 90 CÁPSULAS | D22: 231 | E22: =D22*B22
... B25: 1 | C25: JUSTCETRUX 60 TABS (C.Caducidad) | D25: 56 | E25: =D25*B25
B28: Piezas | C28: Producto | D28: Precio Fact. | E28: Total
B29: 1 | C29: JUSTCOLLAGEN 180 TABLETAS | D29: 263.9154 | E29: =D29*B29
B30: 1 | C30: JUSTFX 120 CÁPSULAS | D30: 338.2455 | E30: =D30*B30
B31: 1 | C31: GLUCOSAMINA 240 TABS | D31: 379.75 | E31: =D31*B31
B32: 1 | C32: PROBIÓTICOS 120 GOMAS | D32: 119.17241 | E32: =D32*B32
B33: 1 | C33: JUSTCETRUX 180 TABS | D33: 133 | E33: =D33*B33
B34: =SUM(B29:B33) | E34: =SUM(E29:E33)

Sheet KITS
A1: KITS SITIO WEB
A3: SISTEMA | B3: CÓDIGOS | C3: PRODUCTOS | D3: Precio unitario normal | E3: Precio facturación normal | F3: Total | G3: Venta -% | I3: Descuento | J3: Precio facturación (-%) | K3: Facturación Total
A4: PACK COLÁGENO BIOTINA | B4: 503635001700 | C4: JustCollagen 111 | D4: 385.004 | E4: 331.9 | F4: 770.008 | G4: 693.0072 | I4: 0.1 | J4: 298.71 | K4: 597.42
B5: 503635004600 | C5: Biotina 110 gomas | D5: 385.004 | E5: 331.9 | I5: 0.1 | J5: 298.71
A6: KIT COLÁGENO TIPO II | B6: 503635000606 | C6: Colágeno Tipo II | D6: 999.0036 | E6: 861.21 | F6: 1998.0072 | G6: 1798.2065 | I6: 0.1 | J6: 775.089 | K6: 1550.178
B7: 503635000606 | C7: Colágeno Tipo II | D7: 999.0036 | E7: 861.21 | I7: 0.1 | J7: 775.089
A8: KIT GLUCOSAMINA 240 | B8: 503635000100 | C8: Glucosamina 240 | D8: 569.0032 | E8: 490.52 | F8: 1138.0064 | G8: 1081.1061 | I8: 0.1 | J8: 441.468 | K8: 882.936
B9: 503635000100 | C9: Glucosamina 240 | D9: 569.0032 | E9: 490.52 | I9: 0.1 | J9: 441.468
A10: KIT JUSTBIO H 110 GOMAS | B10: 503635001600 | C10: JustBio H 110 | D10: 385.004 | E10: 331.9 | F10: 770.008 | G10: 731.5076 | I10: 0.1 | J10: 298.71 | K10: 597.42
B11: 503635001600 | C11: JustBio H 110 | D11: 385.004 | E11: 331.9 | I11: 0.1 | J11: 298.71
A12: KIT JUSTCOLLAGEN 111 GOMAS | B12: 503635001700 | C12: JustCollagen 111 gomitas | D12: 385.004 | E12: 331.9 | F12: 770.008 | G12: 731.5076 | I12: 0.1 | J12: 298.71 | K12: 597.42
B13: 503635001700 | C13: JustCollagen 111 gomitas | D13: 385.004 | E13: 331.9 | I13: 0.1 | J13: 298.71
A14: KIT JUSTCOLLAGEN 180 | B14: 503635002600 | C14: JustCollagen 180 tabs | D14: 366.0032 | E14: 315.52 | F14: 732.0064 | G14: 695.40608 | I14: 0.1 | J14: 283.968 | K14: 567.936
B15: 503635002600 | C15: JustCollagen 180 tabs | D15: 366.0032 | E15: 315.52 | I15: 0.1 | J15: 283.968
A16: KIT JUSTFX 120 | B16: 503635000705 | C16: JustFx 120 | D16: 469.9972 | E16: 405.17 | F16: 939.9944 | G16: 892.99468 | I16: 0.1 | J16: 364.653 | K16: 729.306
B17: 503635000705 | C17: JustFx 120 | D17: 469.9972 | E17: 405.17 | I17: 0.1 | J17: 364.653
A18: KIT JUSTOMEGA 110 GOMAS | B18: 503635001800 | C18: JustOmega 3 110 | D18: 385.004 | E18: 331.9 | F18: 770.008 | G18: 731.5076 | I18: 0.1 | J18: 298.71 | K18: 597.42
B19: 503635001800 | C19: JustOmega 3 110 | D19: 385.004 | E19: 331.9 | I19: 0.1 | J19: 298.71
A20: KIT SISTEMA BELLEZA | B20: 503635000200 | C20: JustCollagen polvo 210 gr | D20: 364.9998 | E20: 314.655 | F20: 1116.007 | G20: 1004.4063 | I20: 0.1 | J20: 283.1895 | K20: 865.8675
B21: 503635002600 | C21: JustCollagen 180 tabs | D21: 366.0032 | E21: 315.52 | I21: 0.1 | J21: 283.968
B22: 503635001700 | C22: JustCollagen 111 gomitas | D22: 385.004 | E22: 331.9 | I22: 0.1 | J22: 298.71
A23: KIT SISTEMA BEST SELLER | B23: 503635002600 | C23: JustCollagen 180 tabs | D23: 366.0032 | E23: 315.52 | F23: 836.0004 | G23: 752.40036 | I23: 0.1 | J23: 283.968 | K23: 648.621
B24: 503635000705 | C24: JustFx 120 | D24: 469.9972 | E24: 405.17 | I24: 0.1 | J24: 364.653
A27: KITS MERCADO LIBRE
A29: SISTEMA | B29: CÓDIGOS | C29: PRODUCTOS | D29: Precio unitario normal | E29: Precio facturación | F29: Total | G29: Venta -% | J29: Facturación por producto | K29: Facturación Total
A30: KIT GLUCOSAMINA JUSTFX + COLÁGENO JUSTCOLLAGEN 90´s | B30: 503635000501 | C30: JustCollagen 90 tabs | D30: 280.0008 | E30: 241.38 | F30: 715.0008 | G30: 643.50072 | I30: 0.1 | J30: 217.242 | K30: 554.742
B31: 503635000900 | C31: JustFx 90 | D31: 435 | E31: 375 | I31: 0.1 | J31: 337.5
A32: KIT BEST SELLER: GLUCOSAMINA JUSTFX + COLÁGENO JUSTCOLLAGEN 120´s | B32: 503635002600 | C32: JustCollagen 180 tabs | D32: 406 | E32: 350 | F32: 926.0048 | G32: 833.40432 | I32: 0.1 | J32: 315 | K32: 718.452
B33: 503635000705 | C33: JustFx 120 | D33: 520.0048 | E33: 448.28 | I33: 0.1 | J33: 403.452
A34: KIT PROBIÓTICOS + OMEGA, 120 GOMITAS | B34: 503635004400 | C34: Probióticos 120 | D34: 315.9956 | E34: 272.41 | F34: 631.9912 | G34: 600.39164 | I34: 0.1 | J34: 245.169 | K34: 490.338
B35: 503635004300 | C35: Omega 120 | D35: 315.9956 | E35: 272.41 | I35: 0.1 | J35: 245.169
A36: KIT GOMITAS DE COLÁGENO 111 + BIOTINA 110 | B36: 503635001700 | C36: JustCollagen 111 | D36: 419.0036 | E36: 361.21 | F36: 838.0072 | G36: 796.10684 | I36: 0.1 | J36: 325.089 | K36: 650.178
B37: 503635004600 | C37: Biotina 110 gomas | D37: 419.0036 | E37: 361.21 | I37: 0.1 | J37: 325.089
A38: KIT JUST OMEGA 3 110 GOMITAS 2 PIEZAS | B38: 503635001800 | C38: JustOmega 3 110 | D38: 419.0036 | E38: 361.21 | F38: 838.0072 | G38: 796.10684 | I38: 0.1 | J38: 325.089 | K38: 650.178
B39: 503635001800 | C39: JustOmega 3 110 | D39: 419.0036 | E39: 361.21 | I39: 0.1 | J39: 325.089
A40: KIT JUST COLLAGEN 111 GOMITAS 2 PIEZAS | B40: 503635001700 | C40: JustCollagen 111 gomitas | D40: 419.0036 | E40: 361.21 | F40: 838.0072 | G40: 796.10684 | I40: 0.1 | J40: 325.089 | K40: 650.178
B41: 503635001700 | C41: JustCollagen 111 gomitas | D41: 419.0036 | E41: 361.21 | I41: 0.1 | J41: 325.089
A42: KIT DE COLÁGENO HIDROLIZADO: POLVO + GOMITAS + TABLETAS | B42: 503635000200 | C42: JustCollagen polvo 210 gr | D42: 419.0036 | E42: 361.21 | F42: 1244.0072 | G42: 1119.6065 | I42: 0.1 | J42: 325.089 | K42: 965.178
B43: 503635002600 | C43: JustCollagen 180 tabs | D43: 406 | E43: 350 | I43: 0.1 | J43: 315
B44: 503635001700 | C44: JustCollagen 111 gomitas | D44: 419.0036 | E44: 361.21 | I44: 0.1 | J44: 325.089
A45: KIT GLUCOSAMINA CONDROITINA + BORO Y MANGANESO 240 TABLETAS 2 PZ | B45: 503635000300 | C45: Glucosamina 240 | D45: 599.0008 | E45: 516.38 | F45: 1198.0016 | G45: 1138.1015 | I45: 0.1 | J45: 464.742 | K45: 929.484
B46: 503635000300 | C46: Glucosamina 240 | D46: 599.0008 | E46: 516.38 | I46: 0.1 | J46: 464.742
A47: KIT BIOTINA + ARÁNDANO JUST BIO H 110 GOMITAS 2 PIEZAS | B47: 503635001600 | C47: JustBio H 110 | D47: 419.0036 | E47: 361.21 | F47: 838.0072 | G47: 796.10684 | I47: 0.1 | J47: 325.089 | K47: 650.178
B48: 503635001600 | C48: JustBio H 110 | D48: 419.0036 | E48: 361.21 | I48: 0.1 | J48: 325.089
A49: KIT JUSTBIOTICS 110 GOMAS 2 PIEZAS | B49: 503635002000 | C49: JustBiotics 110 | D49: 419.0036 | E49: 361.21 | F49: 838.0072 | G49: 796.10684 | I49: 0.1 | J49: 325.089 | K49: 650.178
B50: 503635002000 | C50: JustBiotics 110 | D50: 419.0036 | E50: 361.21 | I50: 0.1 | J50: 325.089
A53: KITS AMAZON
A55: SISTEMA | C55: PRODUCTOS | D55: Precio unitario normal | E55: Precio facturación normal | F55: Total | G55: Venta -% | J55: Facturación por producto | K55: Facturación Total
A56: KIT GLUCOSAMINA JUSTFX + COLÁGENO HIDROLIZADO JUSTCOLLAGEN | B56: 503635002600 | C56: JustCollagen 180 tabs | D56: 406 | E56: 350 | F56: 1044 | G56: 939.6 | I56: 0.1 | J56: 315 | K56: 810
B57: 503635000705 | C57: JustFx 120 | D57: 638 | E57: 550 | I57: 0.1 | J57: 495

Sheet OUTLET ENE 24
A2: Código | B2: PRODUCTOS: | C2: Compra mínima | D2: Precio normal | E2: Precio OUTLET | F2: Precio facturación | G2: Descuento | H2: 2 piezas x | I2: Fecha de caducidad | J2: OV
A3: 503635004300 | B3: GOMITAS OMEGA-3 & DHA 120 PZS | C3: 2 | D3: 267 | E3: 138.84 | F3: 119.68966 | G3: -0.48 | H3: =C3*E3 | I3: 45292 | J3: 230.17241
A4: 503635004600 | B4: GOMITAS BIOTINA & ARANDANO 120 PZS | C4: 2 | D4: 267 | E4: 138.84 | F4: 119.68966 | G4: -0.48 | H4: =C4*E4 | I4: 45261 | J4: 230.17241
A5: 503635004400 | B5: GOMITAS PROBIOTICOS & FIBRA 120 PZS | C5: 2 | D5: 267 | E5: 138.84 | F5: 119.68966 | G5: -0.48 | H5: =C5*E5 | I5: 45261 | J5: 230.17241
A6: 503635004500 | B6: COLÁGENO+BIOTINA 120 GOMAS | C6: 2 | D6: 267 | E6: 138.84 | F6: 119.68966 | G6: -0.48 | H6: =C6*E6 | I6: 45261 | J6: 230.17241
A7: 503635003900 | B7: JUSTCETRUX 180 TABLETAS | C7: 2 | D7: 199 | E7: =D7*0.6 | F7: =E7/1.16 | G7: -0.4 | H7: =C7*E7 | I7: 45047 | J7: 171.55172
A8: 503635003700 | B8: JUSTCETRUX 60 TABLETAS | C8: 2 | D8: 89 | E8: 74.76 | F8: 64.448276 | G8: -0.16 | H8: =C8*E8 | I8: 45108 | J8: 76.724138
A9: 503635000200 | B9: JUSTCOLLAGEN POLVO 210 GRS | C9: 2 | D9: 349 | E9: 174.5 | F9: 149.5 | G9: -0.5 | H9: =C9*E9 | I9: 45200 | J9: 300.86207
A10: 500034000100 | B10: ARISTOCAPS 30 CAPS | C10: 2 | D10: 174 | E10: 99.18 | F10: 99 | G10: -0.43 | H10: =C10*E10 | I10: 45444 | J10: 150
A11: 500034000300 | B11: ARISTOCAPS 90 CAPS | C11: 2 | D11: 399 | E11: =D11*0.5 | F11: =D11*0.5 | G11: -0.5 | H11: =C11*E11 | J11: 343.96552
B12: ONPACK JUSTCOLLAGEN POLVO 210 GRS. | D12: 349 | F12: =(D12*0.6)/1.16 | G12: -0.4 | H12: =C12*E12 | J12: 300.86207
A13: 503635001800 | B13: JUSTOMEGA-3 110 GOMAS | C13: 2 | D13: 390 | E13: =D13*0.5 | F13: =(D13*0.5)/1.16 | G13: -0.5 | H13: =C13*E13 | I13: 45078 | J13: 336.2069
A14: 503635003700 | B14: JUSTCALOSTRO 30 CAPS | C14: 2 | D14: 167 | E14: =D14*0.5 | F14: =(D14*0.5)/1.16 | G14: -0.5 | H14: =C14*E14 | I14: 45444 | J14: 143.96552
A15: 503635001800 | B15: JUST OMEGA 3 110 GOMAS | C15: 2 | D15: 390 | E15: 195 | G15: -0.5 | H15: =C15*E15 | J15: 336.2069

Sheet PreciosACT23
A1: IMPLEMENTACIÓN: 01-MARZO-2023
A2: PLATAFORMA | B2: CÓDIGO | C2: PRODUCTO | D2: Precio de facturación | E2: Precio de venta
A3: AMAZON PRIME | B3: 503635000200 | C3: COLAGENO EN POLVO 210 GR | D3: 315.52 | E3: =D3*1.16
A4: AMAZON PRIME | B4: 503635000606 | C4: COLAGENO TIPO II 90 CAPS | D4: 916.38 | E4: =D4*1.16
A5: AMAZON PRIME | B5: 503635005100 | C5: COLAGENO TIPO II 30 CAPS | D5: 456.04 | E5: =D5*1.16
A6: AMAZON PRIME | B6: 503635000300 | C6: GLUCOSAMINA / CONDROITINA BOVINO 410 TAB | D6: 812.93 | E6: =D6*1.16
A7: AMAZON PRIME | B7: 503635001600 | C7: JUSTBIOH 110 GOMAS | D7: 381.9 | E7: =D7*1.16
A8: AMAZON PRIME | B8: 503635002000 | C8: JUSTBIOTICS 110 GOMAS | D8: 352.59 | E8: =D8*1.16
A9: AMAZON PRIME | B9: 503635001700 | C9: JUSTCOLLAGEN 111 GOMAS | D9: 336.21 | E9: =D9*1.16
A10: AMAZON PRIME | B10: 503635001800 | C10: JUSTOMEGA-3 110 GOMAS | D10: 336.21 | E10: =D10*1.16
A11: AMAZON PRIME | B11: 503635002600 | C11: JUSTCOLLAGEN 180 TABS | D11: 340.52 | E11: =D11*1.16
A12: AMAZON PRIME | B12: 503635000705 | C12: JUSTFX 120 CAPS | D12: 437.07 | E12: =D12*1.16
A13: AMAZON PRIME | B13: 503635001301 | C13: PROBIOTICOS GUMMYCARE 60 GOMAS | D13: 312.93 | E13: =D13*1.16
A14: AMAZON PRIME | B14: 503635004800 | C14: KIT COLÁGENO 90 + BIOTINA 30 (ONPACK) | D14: 257.75862 | E14: =D14*1.16
... A18: AMAZON PRIME | B18: 503635003900 | C18: JUSTCETRUX 180 | D18: 171.55 | E18: =D18*1.16
A19: AMAZON PRIME | B19: 503635005400 | C19: JUSTOLFOCUS 90 CAPS | D19: =E19/1.16 | E19: 493
A20: AMAZON PRIME | B20: 500034000100 | C20: ARISTOCAPS RB 30 CAPS | D20: 174 | E20: 174
A21: AMAZON PRIME | B21: 500034000300 | C21: ARISTOCAPS RB 90 CAPS | D21: 399 | E21: 399
A22: AMAZON VENDEDOR | B22: 503635000200 | C22: COLAGENO EN POLVO 210 GR | D22: 315.52 | E22: =D22*1.16
A23: AMAZON VENDEDOR | B23: 503635000606 | C23: COLAGENO TIPO II 90 CAPS | D23: 916.38 | E23: =D23*1.16
A24: AMAZON VENDEDOR | B24: 503635005100 | C24: COLAGENO TIPO II 30 CAPS | D24: 456.04 | E24: =D24*1.16
A25: AMAZON VENDEDOR | B25: 503635000300 | C25: GLUCOSAMINA / CONDROITINA BOVINO 410 TAB | D25: 812.93 | E25: =D25*1.16
A26: AMAZON VENDEDOR | B26: 503635002000 | C26: JUSTBIOTICS 110 GOMAS | D26: 352.59 | E26: =D26*1.16
A27: AMAZON VENDEDOR | B27: 503635003900 | C27: JUSTCETRUX 180 | D27: 171.55 | E27: =D27*1.16
A28: AMAZON VENDEDOR | B28: 503635001700 | C28: JUSTCOLLAGEN 111 GOMAS | D28: 336.21 | E28: =D28*1.16
A29: AMAZON VENDEDOR | B29: 503635001600 | C29: JUSTBIOH 110 GOMAS | D29: 381.9 | E29: =D29*1.16
A30: AMAZON VENDEDOR | B30: 503635002600 | C30: JUSTCOLLAGEN 180 TABS | D30: 340.52 | E30: =D30*1.16
A31: AMAZON VENDEDOR | B31: 503635000501 | C31: JUSTCOLLAGEN 90 TABS | D31: 212.93 | E31: =D31*1.16
A32: AMAZON VENDEDOR | B32: 503635000705 | C32: JUSTFX 120 CAPS | D32: 437.07 | E32: =D32*1.16
A33: AMAZON VENDEDOR | B33: 503635000900 | C33: JUSTFX 90 CAPS | D33: 336.21 | E33: =D33*1.16
... A36: AMAZON VENDEDOR | B36: 503635004500 | C36: COLÁGENO+BIOTINA 120 GOMAS | D36: 240.52 | E36: =D36*1.16
A37: AMAZON VENDEDOR | B37: 503635005400 | C37: JUSTOLFOCUS 90 CAPS | D37: =E37/1.16 | E37: 493
A38: AMAZON VENDEDOR | B38: 500034000100 | C38: ARISTOCAPS RB 30 CAPS | D38: 174 | E38: 174
A39: AMAZON VENDEDOR | B39: 500034000300 | C39: ARISTOCAPS RB 90 CAPS | D39: 399 | E39: 399
A40: MERCADO LIBRE | B40: 503635000200 | C40: COLAGENO EN POLVO 210 GR | D40: 326.72 | E40: =D40*1.16
A41: MERCADO LIBRE | B41: 503635000606 | C41: COLAGENO TIPO II 90 CAPS | D41: 916.38 | E41: =D41*1.16
A42: MERCADO LIBRE | B42: 503635005100 | C42: COLAGENO TIPO II 30 CAPS | D42: 471.55 | E42: =D42*1.16
A43: MERCADO LIBRE | B43: 503635000300 | C43: GLUCOSAMINA / CONDROITINA BOVINO 410 TAB | D43: 812.93 | E43: =D43*1.16
A44: MERCADO LIBRE | B44: 503635000100 | C44: GLUCOSAMINA / CONDROITINA TIBURON 240 TA | D44: 514.66 | E44: =D44*1.16
A45: MERCADO LIBRE | B45: 503635001600 | C45: JUSTBIOH 110 GOMAS | D45: 381.9 | E45: =D45*1.16
A46: MERCADO LIBRE | B46: 503635002000 | C46: JUSTBIOTICS 110 GOMAS | D46: 352.59 | E46: =D46*1.16
A47: MERCADO LIBRE | B47: 503635003900 | C47: JUSTCETRUX 180 | D47: 171.55 | E47: =D47*1.16
A48: MERCADO LIBRE | B48: 503635003700 | C48: JUSTCETRUX 60 | D48: 83.62 | E48: =D48*1.16
A49: MERCADO LIBRE | B49: 503635001700 | C49: JUSTCOLLAGEN 111 GOMAS | D49: 336.21 | E49: =D49*1.16
A50: MERCADO LIBRE | B50: 503635002600 | C50: JUSTCOLLAGEN 180 TABS | D50: 340.52 | E50: =D50*1.16
A51: MERCADO LIBRE | B51: 503635000501 | C51: JUSTCOLLAGEN 90 TABS | D51: 220 | E51: =D51*1.16
... A61: MERCADO LIBRE | B61: 503635004300 | C61: OMEGA 3 120 GOMAS | D61: 249.14 | E61: =D61*1.16
A62: MERCADO LIBRE | B62: 503635005400 | C62: JUSTOLFOCUS 90 CAPS | D62: =E62/1.16 | E62: 493
A63: MERCADO LIBRE | C63: KIT COLÁGENO (-10%) | D63: 903.105 | E63: =D63*1.16
A64: MERCADO LIBRE | C64: KIT DEPORTE (-10%) | D64: 1075.356 | E64: =D64*1.16
A65: MERCADO LIBRE | C65: KIT BEST SELLER (-10%) | D65: 699.831 | E65: =D65*1.16
A66: MERCADO LIBRE | C66: KIT BEST SELLER 90´S MINI (-10%) | D66: 507.573 | E66: =D66*1.16
A67: MERCADO LIBRE | C67: KIT ESPECIAL (-10%) | D67: 1168.452 | E67: =D67*1.16
A68: MERCADO LIBRE | C68: KIT INMUNE (-10%) | D68: 911.63979 | E68: =D68*1.16
A69: MERCADO LIBRE | C69: KIT GOMAS GRANDES (-10%) | D69: 922.509 | E69: =D69*1.16
A70: MERCADO LIBRE | B70: 500034000100 | C70: ARISTOCAPS RB 30 CAPS | D70: 174 | E70: 174
A71: MERCADO LIBRE | B71: 500034000300 | C71: ARISTOCAPS RB 90 CAPS | D71: 399 | E71: 399
A72: WEB | B72: 503635000200 | C72: COLAGENO EN POLVO 210 GR | D72: 300.86 | E72: =D72*1.16
A73: WEB | B73: 503635000606 | C73: COLAGENO TIPO II 90 CAPS | D73: 912.93 | E73: =D73*1.16
A74: WEB | B74: 503635005100 | C74: COLAGENO TIPO II 30 CAPS | D74: 438.79 | E74: =D74*1.16
A75: WEB | B75: 503635001000 | C75: GLUCOSAMINA / CONDROITINA TIBURON 160 TA | D75: 430.17 | E75: =D75*1.16
A76: WEB | B76: 503635000100 | C76: GLUCOSAMINA / CONDROITINA TIBURON 240 TA | D76: 512.93 | E76: =D76*1.16
A77: WEB | B77: 503635000300 | C77: GLUCOSAMINA / CONDROITINA BOVINO 410 TAB | D77: =E77/1.16 | E77: 940
A78: WEB | B78: 503635001600 | C78: JUSTBIOH 110 GOMAS | D78: 380.17 | E78: =D78*1.16
A79: WEB | B79: 503635002000 | C79: JUSTBIOTICS 110 GOMAS | D79: 350.86 | E79: =D79*1.16
A80: WEB | B80: 503635003900 | C80: JUSTCETRUX 180 | D80: 171.55 | E80: =D80*1.16
A81: WEB | B81: 503635003700 | C81: JUSTCETRUX 60 | D81: 76.72 | E81: =D81*1.16
A82: WEB | B82: 503635001700 | C82: JUSTCOLLAGEN 111 GOMAS | D82: =E82/1.16 | E82: 389
A83: WEB | B83: 503635002600 | C83: JUSTCOLLAGEN 180 TABS | D83: 340.52 | E83: =D83*1.16
A84: WEB | B84: 503635000501 | C84: JUSTCOLLAGEN 90 TABS | D84: =E84/1.16 | E84: 220
A85: WEB | B85: 503635000705 | C85: JUSTFX 120 CAPS | D85: =E85/1.16 | E85: 505
A86: WEB | B86: 503635000900 | C86: JUSTFX 90 CAPS | D86: 318.1 | E86: =D86*1.16
A87: WEB | B87: 503635003700 | C87: JUSTCALOSTRO 30 CAPS | D87: 143.96552 | E87: =D87*1.16
A88: WEB | B88: 503635001800 | C88: JUSTOMEGA-3 110 GOMAS | D88: 336.21 | E88: =D88*1.16
A89: WEB | B89: 503635001301 | C89: PROBIOTICOS GUMMYCARE 60 GOMAS | D89: 300.86 | E89: =D89*1.16
A90: WEB | B90: 503635004500 | C90: COLÁGENO+BIOTINA 120 GOMAS | D90: 230.17 | E90: =D90*1.16
A91: WEB | B91: 503635004400 | C91: PROBIÓTICOS + FIBRA 120 GOMAS | D91: 230.17 | E91: =D91*1.16
A92: WEB | B92: 503635004300 | C92: OMEGA 3 120 GOMAS | D92: 230.17 | E92: =D92*1.16
A93: WEB | B93: 503635004600 | C93: BIOTINA 120 GOMAS | D93: 230.17 | E93: =D93*1.16
A94: WEB | B94: 503635005400 | C94: JUSTOLFOCUS 90 CAPS | D94: =E94/1.16 | E94: 489
A95: WEB | C95: SISTEMA BELLEZA (-10%) | D95: 879.05234 | E95: =D95*1.16
A96: WEB | C96: SISTEMA DEPORTE (-10%) | D96: 1050.516 | E96: =D96*1.16
A97: WEB | C97: SISTEMA BEST SELLER (-10%) | D97: 698.27834 | E97: =D97*1.16
A98: WEB | C98: KIT MOTÍVATE (-10%) | D98: 990.77369 | E98: =D98*1.16
A99: WEB | B99: 500034000100 | C99: ARISTOCAPS RB 30 CAPS | D99: 174 | E99: 174
A100: WEB | B100: 500034000300 | C100: ARISTOCAPS RB 90 CAPS | D100: 399 | E100: 399

Sheet Buen fin
A1: LISTADO DE PRECIOS E-COMM | E1: -30% Buen Fin
A2: PLATAFORMA | B2: PRODUCTO | C2: Precio de facturación | D2: Precio de venta | E2: Precio de facturación | F2: Precio de venta
A3: AMAZON PRIME | B3: COLAGENO EN POLVO 210 GR | C3: =D3/1.16 | D3: 385 | E3: =F3/1.16 | F3: =D3*0.7
A4: AMAZON PRIME | B4: COLAGENO TIPO II 90 CAPS | C4: =D4/1.16 | D4: 997 | E4: =F4/1.16 | F4: =D4*0.7
A5: AMAZON PRIME | B5: GLUCOSAMINA / CONDROITINA BOVINO 410 TAB | C5: =D5/1.16 | D5: 943 | E5: =F5/1.16 | F5: =D5*0.7
A6: AMAZON PRIME | B6: JUSTBIOH 110 GOMAS | C6: =D6/1.16 | D6: 443 | E6: =F6/1.16 | F6: =D6*0.7
A7: AMAZON PRIME | B7: JUSTBIOTICS 110 GOMAS | C7: =D7/1.16 | D7: 409 | E7: =F7/1.16 | F7: =D7*0.7
A8: AMAZON PRIME | B8: JUSTCOLLAGEN 111 GOMAS | C8: =D8/1.16 | D8: 390 | E8: =F8/1.16 | F8: =D8*0.7
A9: AMAZON PRIME | B9: JUSTOMEGA-3 110 GOMAS | C9: =D9/1.16 | D9: 390 | E9: =F9/1.16 | F9: =D9*0.7
A10: AMAZON PRIME | B10: JUSTCOLLAGEN 180 TABS | C10: =D10/1.16 | D10: 395 | E10: =F10/1.16 | F10: =D10*0.7
A11: AMAZON PRIME | B11: JUSTFX 120 CAPS | C11: =D11/1.16 | D11: 507 | E11: =F11/1.16 | F11: =D11*0.7
A12: AMAZON PRIME | B12: PROBIOTICOS GUMMYCARE 60 GOMAS | C12: =D12/1.16 | D12: 363 | E12: =F12/1.16 | F12: =D12*0.7
A13: AMAZON PRIME | B13: COLÁGENO+BIOTINA 120 GOMAS | C13: =D13/1.16 | D13: 280 | E13: =F13/1.16 | F13: =D13*0.7
A14: AMAZON PRIME | B14: PROBIÓTICOS+FIBRA 120 GOMAS | C14: =D14/1.16 | D14: 280 | E14: =F14/1.16 | F14: =D14*0.7
... A35: AMAZON VENDEDOR | B35: JUSTOLFOCUS 90 CAPS | C35: =D35/1.16 | D35: 493 | E35: =F35/1.16 | F35: =D35*0.7
A36: AMAZON VENDEDOR | B36: KIT BEST SELLER (-10%) | C36: =D36/1.16 | D36: 811.8 | E36: - | F36: -
A37: MERCADO LIBRE | B37: COLAGENO EN POLVO 210 GR | C37: =D37/1.16 | D37: 379 | E37: =F37/1.16 | F37: =D37*0.7
A38: MERCADO LIBRE | B38: COLAGENO TIPO II 90 CAPS | C38: =D38/1.16 | D38: 1063 | E38: =F38/1.16 | F38: =D38*0.7
A39: MERCADO LIBRE | B39: COLAGENO TIPO II 30 CAPS | C39: =D39/1.16 | D39: 547 | E39: =F39/1.16 | F39: =D39*0.7
A40: MERCADO LIBRE | B40: GLUCOSAMINA / CONDROITINA BOVINO 410 TAB | C40: =D40/1.16 | D40: 943 | E40: =F40/1.16 | F40: =D40*0.7
A41: MERCADO LIBRE | B41: GLUCOSAMINA / CONDROITINA TIBURON 240 TA | C41: =D41/1.16 | D41: 597.01 | E41: =F41/1.16 | F41: =D41*0.7
A42: MERCADO LIBRE | B42: JUSTBIOH 110 GOMAS | C42: =D42/1.16 | D42: 443 | E42: =F42/1.16 | F42: =D42*0.7
A43: MERCADO LIBRE | B43: JUSTBIOTICS 110 GOMAS | C43: =D43/1.16 | D43: 409 | E43: =F43/1.16 | F43: =D43*0.7
A44: MERCADO LIBRE | B44: JUSTCETRUX 180 | C44: 219.83 | D44: 199 | E44: =F44/1.16 | F44: =D44*0.7
A45: MERCADO LIBRE | B45: JUSTCETRUX 60 | C45: 107.76 | D45: 97 | E45: - | F45: -
A46: MERCADO LIBRE | B46: JUSTCOLLAGEN 111 GOMAS | C46: =D46/1.16 | D46: 390 | E46: =F46/1.16 | F46: =D46*0.7
A47: MERCADO LIBRE | B47: JUSTCOLLAGEN 180 TABS | C47: =D47/1.16 | D47: 395 | E47: =F47/1.16 | F47: =D47*0.7
A48: MERCADO LIBRE | B48: JUSTCOLLAGEN 90 TABS | C48: =D48/1.16 | D48: 255.2 | E48: =F48/1.16 | F48: =D48*0.7
A49: MERCADO LIBRE | B49: JUSTFX 120 CAPS | C49: =D49/1.16 | D49: 507 | E49: =F49/1.16 | F49: =D49*0.7
A50: MERCADO LIBRE | B50: JUSTFX 90 CAPS | C50: =D50/1.16 | D50: 399.01 | E50: =F50/1.16 | F50: =D50*0.7
A51: MERCADO LIBRE | B51: JUSTOLFOCUS 90 CAPS | C51: =D51/1.16 | D51: 493 | E51: =F51/1.16 | F51: =D51*0.7
A52: MERCADO LIBRE | B52: JUSTOMEGA-3 110 GOMAS | C52: =D52/1.16 | D52: 390 | E52: =F52/1.16 | F52: =D52*0.7
A53: MERCADO LIBRE | B53: PROBIOTICOS GUMMYCARE 60 GOMAS | C53: =D53/1.16 | D53: 375 | E53: =F53/1.16 | F53: =D53*0.7
A54: MERCADO LIBRE | B54: Kit De Colágeno Hidrolizado: Polvo + Gomitas + Tabletas | C54: =D54/1.16 | D54: 1047.6 | E54: - | F54: -
A55: MERCADO LIBRE | B55: KIT GOMITAS | C55: =D55/1.16 | D55: 1070.11 | E55: - | F55: -
A56: MERCADO LIBRE | B56: Kit Gomitas De Colágeno + Biotina | C56: =D56/1.16 | D56: 645.06 | E56: - | F56: -
A57: MERCADO LIBRE | B57: PACK GLUCOSAMINA 240 2PZS | C57: =D57/1.16 | D57: 1134.31 | E57: - | F57: -
A58: MERCADO LIBRE | B58: PACK BIOTINA 110 GOMAS 2PZS | C58: =D58/1.16 | D58: 841.71 | E58: - | F58: -
A59: MERCADO LIBRE | B59: PACK JUSTCOLLAGEN 111 GOMAS 2PZS | C59: =D59/1.16 | D59: 741.01 | E59: - | F59: -
A60: MERCADO LIBRE | B60: Kit Probióticos + Omega, 120 Gomitas | C60: =D60/1.16 | D60: 549.1 | E60: - | F60: -
A61: MERCADO LIBRE | B61: COLÁGENO+BIOTINA 120 GOMAS | C61: =D61/1.16 | D61: 288 | E61: =F61/1.16 | F61: =D61*0.7
A62: MERCADO LIBRE | B62: PROBIÓTICOS+FIBRA 120 GOMAS | C62: =D62/1.16 | D62: 289 | E62: =F62/1.16 | F62: =D62*0.7
A63: MERCADO LIBRE | B63: OMEGA3 DHA 120 GOMAS | C63: =D63/1.16 | D63: 289 | E63: =F63/1.16 | F63: =D63*0.7
A64: MERCADO LIBRE | B64: BIOTINA 120 GOMAS | C64: =D64/1.16 | D64: 289 | E64: =F64/1.16 | F64: =D64*0.7
A65: WEB | B65: COLAGENO EN POLVO 210 GR | C65: =D65/1.16 | D65: 349 | E65: =F65/1.16 | F65: =D65*0.7
A66: WEB | B66: COLAGENO TIPO II 90 CAPS | C66: =D66/1.16 | D66: 1059 | E66: =F66/1.16 | F66: =D66*0.7
A67: WEB | B67: COLAGENO TIPO II 30 CAPS | C67: =D67/1.16 | D67: 509 | E67: =F67/1.16 | F67: =D67*0.7
A68: WEB | B68: GLUCOSAMINA / CONDROITINA TIBURON 160 TA | C68: =D68/1.16 | D68: 499 | E68: =F68/1.16 | F68: =D68*0.7
A69: WEB | B69: GLUCOSAMINA / CONDROITINA TIBURON 240 TA | C69: =D69/1.16 | D69: 595 | E69: =F69/1.16 | F69: =D69*0.7
A70: WEB | B70: GLUCOSAMINA / CONDROITINA BOVINO 410 TAB | C70: =D70/1.16 | D70: 940 | E70: =F70/1.16 | F70: =D70*0.7
A71: WEB | B71: JUSTBIOH 110 GOMAS | C71: =D71/1.16 | D71: 441 | E71: =F71/1.16 | F71: =D71*0.7
A72: WEB | B72: JUSTBIOTICS 110 GOMAS | C72: =D72/1.16 | D72: 407 | E72: =F72/1.16 | F72: =D72*0.7
A73: WEB | B73: JUSTCETRUX 180 | C73: 206.035 | D73: 199 | E73: =F73/1.16 | F73: =D73*0.7
A74: WEB | B74: JUSTCETRUX 60 | C74: 105.17 | D74: 89 | E74: - | F74: -
A75: WEB | B75: JUSTCOLLAGEN 111 GOMAS | C75: =D75/1.16 | D75: 389 | E75: =F75/1.16 | F75: =D75*0.7
A76: WEB | B76: JUSTCOLLAGEN 180 TABS | C76: =D76/1.16 | D76: 395 | E76: =F76/1.16 | F76: =D76*0.7
A77: WEB | B77: JUSTCOLLAGEN 90 TABS | C77: =D77/1.16 | D77: 220 | E77: =F77/1.16 | F77: =D77*0.7
A78: WEB | B78: JUSTFX 120 CAPS | C78: =D78/1.16 | D78: 505 | E78: =F78/1.16 | F78: =D78*0.7
A79: WEB | B79: JUSTFX 90 CAPS | C79: =D79/1.16 | D79: 369 | E79: =F79/1.16 | F79: =D79*0.7
A80: WEB | B80: JUSTOLFOCUS 90 CAPS | C80: =D80/1.16 | D80: 489 | E80: =F80/1.16 | F80: =D80*0.7
A81: WEB | B81: JUSTCALOSTRO 30 CAPS | C81: =D81/1.16 | D81: 167 | E81: - | F81: -
A82: WEB | B82: JUSTOMEGA-3 110 GOMAS | C82: =D82/1.16 | D82: 390 | E82: =F82/1.16 | F82: =D82*0.7
A83: WEB | B83: PROBIOTICOS GUMMYCARE 60 GOMAS | C83: =D83/1.16 | D83: 349 | E83: =F83/1.16 | F83: =D83*0.7
A84: WEB | B84: SISTEMA BELLEZA (-10%) | C84: =D84/1.16 | D84: 1019.7 | E84: - | F84: -
A85: WEB | B85: SISTEMA DEPORTE (-10%) | C85: =D85/1.16 | D85: 1218.6 | E85: - | F85: -
A86: WEB | B86: SISTEMA BEST SELLER (-10%) | C86: =D86/1.16 | D86: 810 | E86: - | F86: -
A87: WEB | B87: PACK 2 PZS COLAGENO TIPO II | C87: =D87/1.16 | D87: 2012.1 | E87: - | F87: -
A88: WEB | B88: PACK 2 PZS GLUCOSAMINA 240 | C88: =D88/1.16 | D88: 1130.5 | E88: - | F88: -
A89: WEB | B89: PACK 2 PZS JUSTBIOH 110 GOMAS | C89: =D89/1.16 | D89: 837.89 | E89: - | F89: -
A90: WEB | B90: PACK 2 PZS JUSTCOLLAGEN 111 GOMAS | C90: =D90/1.16 | D90: 739.1 | E90: - | F90: -
A91: WEB | B91: PACK 2 PZS JUSTCOLLAGEN 180 | C91: =D91/1.16 | D91: 750.51 | E91: - | F91: -
A92: WEB | B92: PACK 2 PZS JUSTFX 120 CAPS | C92: =D92/1.16 | D92: 959.5 | E92: - | F92: -
A93: WEB | B93: PACK 2 PZS JUSTOMEGA3 110 GOMAS | C93: =D93/1.16 | D93: 741 | E93: - | F93: -
A94: WEB | B94: KIT PROBIOTICOS + OMEGA 120 GOMAS | C94: =D94/1.16 | D94: 507.29 | E94: - | F94: -
A95: WEB | B95: KIT GOMITAS DE COLÁGENO + BIOTINA | C95: =D95/1.16 | D95: 623.2 | E95: - | F95: -

Sheet Form Ecom
A1: Plataforma | B1: Código | E1: COSTO DE ENVIO
A2: Mercado Libre | C2: Precio de facturación | E2: Mercado Libre | F2: 0
A3: COLAGENO EN POLVO 210 GR | B3: 503635000200 | C3: 326.72 | E3: Just for you | F3: 76.72
A4: COLAGENO TIPO II 90 CAPS | B4: 503635000606 | C4: 916.38 | E4: Amazon | F4: 81.9
A5: COLAGENO TIPO II 30 CAPS | B5: 503635005100 | C5: 471.55
A6: GLUCOSAMINA / CONDROITINA BOVINO 410 TAB | B6: 503635000300 | C6: 812.93
A7: GLUCOSAMINA / CONDROITINA TIBURON 240 TA | B7: 503635000100 | C7: 514.66
A8: JUSTBIOH 110 GOMAS | B8: 503635001600 | C8: 381.9
A9: JUSTBIOTICS 110 GOMAS | B9: 503635002000 | C9: 352.59
A10: JUSTCETRUX 60 | B10: 503635003700 | C10: 83.62
A11: JUSTCOLLAGEN 111 GOMAS | B11: 503635001700 | C11: 336.21
A12: JUSTCOLLAGEN 180 TABS | B12: 503635002600 | C12: 340.52
A13: JUSTCOLLAGEN 90 TABS | B13: 503635000501 | C13: 220
A14: JUSTFX 120 CAPS | B14: 503635000705 | C14: 437.07
A15: JUSTFX 90 CAPS | B15: 503635000900 | C15: 343.97
A16: JUSTCALOSTRO 30 CAPS | B16: 503635004200 | C16: 162.93103
... A22: OMEGA 3 120 GOMAS | B22: 503635004300 | C22: 249.14

Sheet KITS JFY ACT 23
A1: KITS SITIO WEB:
A3: SISTEMA | B3: CÓDIGOS | C3: PRODUCTOS | D3: Precio unitario normal | E3: Precio facturación normal | F3: Total | G3: Venta -% | I3: Descuento | J3: Precio facturación (-%) | K3: Facturación Total
A4: SISTEMA BELLEZA | B4: 503635000200 | C4: JustCollagen polvo 210 gr | D4: 643.50072 | E4: =D4/1.16 | F4: =D4+D5+D6 | G4: =F4*0.9 | I4: 0.1 | J4: =(D4*0.9)/1.16 | K4: =SUM(J4:J6)
B5: 503635002600 | C5: JustCollagen 180 tabs | D5: 245.0036 | E5: =D5/1.16 | I5: 0.1 | J5: =(D5*0.9)/1.16
B6: 503635001700 | C6: JustCollagen 111 gomitas | D6: 366.0032 | E6: =D6/1.16 | I6: 0.1 | J6: =(D6*0.9)/1.16
A7: SISTEMA DEPORTE | B7: 503635000900 | C7: JustFx 90 | D7: 385.004 | E7: =D7/1.16 | F7: =D7+D8+D9 | G7: =F7*0.9 | I7: 0.1 | J7: =(D7*0.9)/1.16 | K7: =SUM(J7:J9)
B8: 503635000300 | C8: Glucosamina 240 | D8: 754.20648 | E8: =D8/1.16 | I8: 0.1 | J8: =(D8*0.9)/1.16
B9: 503635001800 | C9: JustOmega 3 110 | D9: 145 | E9: =D9/1.16 | I9: 0.1 | J9: =(D9*0.9)/1.16
A10: SISTEMA BEST SELLER | B10: 503635002600 | C10: JustCollagen 180 tabs | D10: 245.0036 | E10: =D10/1.16 | F10: =D10+D11 | G10: =F10*0.9 | I10: 0.1 | J10: =(D10*0.9)/1.16 | K10: =J10+J11
B11: 503635000705 | C11: JustFx 120 | D11: 364.9998 | E11: =D11/1.16 | I11: 0.1 | J11: =(D11*0.9)/1.16
A12: PACK JUSTFX 120 | B12: 503635000705 | C12: JustFx 120 | D12: 364.9998 | E12: =D12/1.16 | F12: =D12+D13 | G12: =F12*0.95 | I12: 0.05 | J12: =(D12*0.95)/1.16 | K12: =J12+J13
B13: 503635000705 | C13: JustFx 120 | D13: 364.9998 | E13: =D13/1.16 | I13: 0.05 | J13: =(D13*0.95)/1.16
A14: PACK JUSTCOLLAGEN 180 | B14: 503635002600 | C14: JustCollagen 180 tabs | D14: 245.0036 | E14: =D14/1.16 | F14: =D14+D15 | G14: =F14*0.95 | I14: 0.05 | J14: =(D14*0.95)/1.16 | K14: =J14+J15
B15: 503635002600 | C15: JustCollagen 180 tabs | D15: 245.0036 | E15: =D15/1.16 | I15: 0.05 | J15: =(D15*0.95)/1.16
A16: PACK JUSTOMEGA 110 GOMAS | B16: 503635001800 | C16: JustOmega 3 110 | D16: 390 | E16: =D16/1.16 | F16: =D16+D17 | G16: =F16*0.95 | I16: 0.05 | J16: =(D16*0.95)/1.16 | K16: =J16+J17
B17: 503635001800 | C17: JustOmega 3 110 | D17: 390 | E17: =D17/1.16 | I17: 0.05 | J17: =(D17*0.95)/1.16
A18: PACK JUSTBIOTICS 110 GOMAS | B18: 503635002000 | C18: JustBiotics 110 | D18: 1078.2014 | E18: =D18/1.16 | F18: =D18+D19 | G18: =F18*0.95 | I18: 0.05 | J18: =(D18*0.95)/1.16 | K18: =J18+J19
B19: 503635002000 | C19: JustBiotics 110 | D19: 1078.2014 | E19: =D19/1.16 | I19: 0.05 | J19: =(D19*0.95)/1.16
A20: PACK JUSTBIO H 110 GOMAS | B20: 503635001600 | C20: JustBio H 110 | D20: 1119.6065 | E20: =D20/1.16 | F20: =D20+D21 | G20: =F20*0.95 | I20: 0.05 | J20: =(D20*0.95)/1.16 | K20: =J20+J21
B21: 503635001600 | C21: JustBio H 110 | D21: 1119.6065 | E21: =D21/1.16 | I21: 0.05 | J21: =(D21*0.95)/1.16
A22: PACK JUSTCOLLAGEN 111 GOMAS | B22: 503635001700 | C22: JustCollagen 111 gomitas | D22: 366.0032 | E22: =D22/1.16 | F22: =D22+D23 | G22: =F22*0.95 | I22: 0.05 | J22: =(D22*0.95)/1.16 | K22: =J22+J23
B23: 503635001700 | C23: JustCollagen 111 gomitas | D23: 366.0032 | E23: =D23/1.16 | I23: 0.05 | J23: =(D23*0.95)/1.16
A24: PACK COLÁGENO TIPO II | B24: 503635000606 | C24: Colágeno Tipo II | D24: 833.40432 | E24: =D24/1.16 | F24: =D24+D25 | G24: =F24*0.95 | I24: 0.05 | J24: =(D24*0.95)/1.16 | K24: =J24+J25
B25: 503635000606 | C25: Colágeno Tipo II | D25: 833.40432 | E25: =D25/1.16 | I25: 0.05 | J25: =(D25*0.95)/1.16
A26: PACK GLUCOSAMINA 240 | B26: 503635000100 | C26: Glucosamina 240 | D26: 754.20648 | E26: =D26/1.16 | F26: =D26+D27 | G26: =F26*0.95 | I26: 0.05 | J26: =(D26*0.95)/1.16 | K26: =J26+J27
B27: 503635000100 | C27: Glucosamina 240 | D27: 754.20648 | E27: =D27/1.16 | I27: 0.05 | J27: =(D27*0.95)/1.16
A28: PACK COLÁGENO BIOTINA | B28: 503635001700 | C28: JustCollagen 111 | D28: 366.0032 | E28: =D28/1.16 | F28: =D28+D29 | G28: =F28*0.95 | I28: 0.05 | J28: =(D28*0.95)/1.16 | K28: =J28+J29
B29: 503635004600 | C29: Biotina 120 gomas | D29: 392.9964 | E29: =D29/1.16 | I29: 0.05 | J29: =(D29*0.95)/1.16
A30: PACK PROBIÓTICOS OMEGA | B30: 503635004400 | C30: Probióticos + Fibra 120 | D30: 145 | E30: =D30/1.16 | F30: =D30+D31 | G30: =F30*0.95 | I30: 0.05 | J30: =(D30*0.95)/1.16 | K30: =J30+J31
B31: 503635004300 | C31: Omega 120 | D31: 469.9972 | E31: =D31/1.16 | I31: 0.05 | J31: =(D31*0.95)/1.16
A33: KITS MERCADO LIBRE
A35: SISTEMA | C35: PRODUCTOS | D35: Precio unitario normal | E35: Precio facturación | F35: Total | G35: Venta -% | J35: Facturación por producto | K35: Facturación Total
A36: KIT COLÁGENO | B36: 503635000200 | C36: JustCollagen polvo 210 gr | D36: 280.0008 | E36: =D36/1.16 | F36: =D36+D37+D38 | G36: =F36*0.9 | I36: 0.1 | J36: =(D36*0.9)/1.16 | K36: =SUM(J36:J38)
B37: 503635002600 | C37: JustCollagen 180 tabs | D37: 160.4976 | E37: =D37/1.16 | I37: 0.1 | J37: =(D37*0.9)/1.16
B38: 503635001700 | C38: JustCollagen 111 gomitas | D38: 315.9956 | E38: =D38/1.16 | I38: 0.1 | J38: =(D38*0.9)/1.16
A39: KIT DEPORTE | B39: 503635000900 | C39: JustFx 90 | D39: 154.9992 | E39: =D39/1.16 | F39: =D39+D40+D41 | G39: =F39*0.9 | I39: 0.1 | J39: =(D39*0.9)/1.16 | K39: =SUM(J39:J41)
B40: 503635000100 | C40: Glucosamina 240 | D40: 419.0036 | E40: =D40/1.16 | I40: 0.1 | J40: =(D40*0.9)/1.16
B41: 503635001800 | C41: JustOmega 3 110 | D41: 415.0016 | E41: =D41/1.16 | I41: 0.1 | J41: =(D41*0.9)/1.16
A42: KIT BEST SELLER | B42: 503635002600 | C42: JustCollagen 180 tabs | D42: 160.4976 | E42: =D42/1.16 | F42: =D42+D43 | G42: =F42*0.9 | I42: 0.1 | J42: =(D42*0.9)/1.16 | K42: =J42+J43
B43: 503635000705 | C43: JustFx 120 | D43: 435 | E43: =D43/1.16 | I43: 0.1 | J43: =(D43*0.9)/1.16
A44: PACK COLÁGENO | C44: JustCollagen polvo 210 gr | F44: =D44+D45 | G44: N/A | I44: 0.1 | J44: =D44/1.16 | K44: =J44+J45
C45: JustCollagen 111 gomitas | I45: 0.1 | J45: =D45/1.16
A46: KIT GOMAS | B46: 503635002000 | C46: JustBiotics 110 gomas | D46: 315.9956 | E46: =D46/1.16 | F46: =D46+D47+D48 | G46: =F46*0.9 | I46: 0.1 | J46: =(D46*0.9)/1.16 | K46: =SUM(J46:J48)
B47: 503635001800 | C47: JustOmega 3 110 gomas | D47: 415.0016 | E47: =D47/1.16 | I47: 0.1 | J47: =(D47*0.9)/1.16
B48: 503635001700 | C48: JustCollagen 111 gomitas | D48: 315.9956 | E48: =D48/1.16 | I48: 0.1 | J48: =(D48*0.9)/1.16
A49: KIT BEST SELLER MINI | B49: 503635000501 | C49: JustCollagen 90 tabs | D49: 520.0048 | E49: =D49/1.16 | F49: =D49+D50 | G49: =F49*0.9 | I49: 0.1 | J49: =(D49*0.9)/1.16 | K49: =J49+J50
B50: 503635000900 | C50: JustFx 90 | D50: 154.9992 | E50: =D50/1.16 | I50: 0.1 | J50: =(D50*0.9)/1.16
A51: KIT ESPECIAL | B51: 503635000200 | C51: JustCollagen polvo 210 gr | D51: 280.0008 | E51: =D51/1.16 | F51: =D51+D52+D54+D53 | G51: =F51*0.9 | I51: 0.1 | J51: =(D51*0.9)/1.16 | K51: =SUM(J51:J54)
B52: 503635002600 | C52: JustCollagen 180 tabs | D52: 160.4976 | E52: =D52/1.16 | I52: 0.1 | J52: =(D52*0.9)/1.16
B53: 503635001600 | C53: JustBio H 110 gomas | D53: 419.0036 | E53: =D53/1.16 | I53: 0.1 | J53: =(D53*0.9)/1.16
B54: 503635004400 | C54: Probióticos + Fibra 120 | D54: 315.9956 | E54: =D54/1.16 | I54: 0.1 | J54: =(D54*0.9)/1.16
A55: PACK JUSTOMEGA 110 GOMAS | B55: 503635001800 | C55: JustOmega 3 110 | D55: 415.0016 | E55: =D55/1.16 | F55: =D55+D56 | G55: =F55*0.95 | I55: 0.05 | J55: =(D55*0.95)/1.16 | K55: =J55+J56
B56: 503635001800 | C56: JustOmega 3 110 | D56: 415.0016 | E56: =D56/1.16 | I56: 0.05 | J56: =(D56*0.95)/1.16
A57: PACK JUSTBIOTICS 110 GOMAS | B57: 503635002000 | C57: JustBiotics 110 | D57: 315.9956 | E57: =D57/1.16 | F57: =D57+D58 | G57: =F57*0.95 | I57: 0.05 | J57: =(D57*0.95)/1.16 | K57: =J57+J58
B58: 503635002000 | C58: JustBiotics 110 | D58: 315.9956 | E58: =D58/1.16 | I58: 0.05 | J58: =(D58*0.95)/1.16
A59: PACK JUSTBIO H 110 GOMAS | B59: 503635001600 | C59: JustBio H 110 | D59: 419.0036 | E59: =D59/1.16 | F59: =D59+D60 | G59: =F59*0.95 | I59: 0.05 | J59: =(D59*0.95)/1.16 | K59: =J59+J60
B60: 503635001600 | C60: JustBio H 110 | D60: 419.0036 | E60: =D60/1.16 | I60: 0.05 | J60: =(D60*0.95)/1.16
A61: PACK JUSTCOLLAGEN 111 GOMAS | B61: 503635001700 | C61: JustCollagen 111 gomitas | D61: 315.9956 | E61: =D61/1.16 | F61: =D61+D62 | G61: =F61*0.95 | I61: 0.05 | J61: =(D61*0.95)/1.16 | K61: =J61+J62
B62: 503635001700 | C62: JustCollagen 111 gomitas | D62: 315.9956 | E62: =D62/1.16 | I62: 0.05 | J62: =(D62*0.95)/1.16
A63: PACK COLÁGENO TIPO II | C63: Colágeno Tipo II | F63: =D63+D64 | G63: =F63*0.95 | I63: 0.05 | J63: =(D63*0.95)/1.16 | K63: =J63+J64
C64: Colágeno Tipo II | I64: 0.05 | J64: =(D64*0.95)/1.16
A65: PACK GLUCOSAMINA 240 | B65: 503635000300 | C65: Glucosamina 240 | D65: 419.0036 | E65: =D65/1.16 | F65: =D65+D66 | G65: =F65*0.95 | I65: 0.05 | J65: =(D65*0.95)/1.16 | K65: =J65+J66
B66: 503635000300 | C66: Glucosamina 240 | D66: 419.0036 | E66: =D66/1.16 | I66: 0.05 | J66: =(D66*0.95)/1.16
A67: PACK COLÁGENO BIOTINA | B67: 503635001700 | C67: JustCollagen 111 | D67: 315.9956 | E67: =D67/1.16 | F67: =D67+D68 | G67: =F67*0.95 | I67: 0.05 | J67: =(D67*0.95)/1.16 | K67: =J67+J68
B68: 503635004600 | C68: Biotina 120 gomas | D68: 160.4976 | E68: =D68/1.16 | I68: 0.05 | J68: =(D68*0.95)/1.16
A69: PACK PROBIÓTICOS OMEGA | B69: 503635004400 | C69: Probióticos 120 | D69: 315.9956 | E69: =D69/1.16 | F69: =D69+D70 | G69: =F69*0.95 | I69: 0.05 | J69: =(D69*0.95)/1.16 | K69: =J69+J70
B70: 503635004300 | C70: Omega 120 | D70: 493 | E70: =D70/1.16 | I70: 0.05 | J70: =(D70*0.95)/1.16
A72: KITS AMAZON
A74: SISTEMA | C74: PRODUCTOS | D74: Precio unitario normal | E74: Precio facturación normal | F74: Total | G74: Venta -% | J74: Facturación por producto | K74: Facturación Total
A75: SISTEMA BEST SELLER | B75: 503635002600 | C75: JustCollagen 180 tabs | D75: 315.9956 | E75: =D75/1.16 | F75: =D75+D76 | G75: =F75*0.9 | I75: 0.1 | J75: =(D75*0.9)/1.16 | K75: =J75+J76
B76: 503635000705 | C76: JustFx 120 | D76: 397.996 | E76: =D76/1.16 | I76: 0.1 | J76: =(D76*0.9)/1.16
A77: SISTEMA BELLEZA | B77: 503635000200 | C77: JustCollagen polvo 210 gr | D77: 0 | E77: =D77/1.16 | F77: =D77+D78+D79 | G77: =F77*0.9 | I77: 0.1 | J77: =(D77*0.9)/1.16 | K77: =SUM(J77:J79)
B78: 503635002600 | C78: JustCollagen 180 tabs | D78: 315.9956 | E78: =D78/1.16 | I78: 0.1 | J78: =(D78*0.9)/1.16
B79: 503635001700 | C79: JustCollagen 111 gomitas | D79: 160.4976 | E79: =D79/1.16 | I79: 0.1 | J79: =(D79*0.9)/1.16

Sheet OUTLET 26.07.23
A2: Código | B2: PRODUCTOS: | C2: Compra mínima | D2: Precio unitario normal | E2: Precio unitario facturación | F2: Descuento | G2: Precio público OUTLET | H2: Precio unitario facturación | I2: 2 piezas x | J2: Fecha de caducidad
A3: 503635004300 | B3: GOMITAS OMEGA-3 & DHA 120 PZS | C3: 2 | D3: 267 | E3: =D3/1.16 | F3: -0.48 | G3: =D3*0.52 | H3: =G3/1.16 | I3: =C3*G3 | J3: 45292
A4: 503635004600 | B4: GOMITAS BIOTINA & ARANDANO 120 PZS | C4: 2 | D4: 267 | E4: =D4/1.16 | F4: -0.48 | G4: =D4*0.52 | H4: =G4/1.16 | I4: =C4*G4 | J4: 45261
A5: 503635004400 | B5: GOMITAS PROBIOTICOS & FIBRA 120 PZS | C5: 2 | D5: 267 | E5: =D5/1.16 | F5: -0.48 | G5: =D5*0.52 | H5: =G5/1.16 | I5: =C5*G5 | J5: 45261
A6: 503635004500 | B6: COLÁGENO+BIOTINA 120 GOMAS | C6: 2 | D6: 267 | E6: =D6/1.16 | F6: -0.48 | G6: =D6*0.52 | H6: =G6/1.16 | I6: =C6*G6 | J6: 45261
A7: 503635003900 | B7: JUSTCETRUX 180 TABLETAS | C7: 2 | E7: =D7/1.16 | F7: -0.5 | G7: 119.5003 | H7: =G7/1.16 | I7: =C7*G7 | J7: 45047
A8: 503635003700 | B8: JUSTCETRUX 60 TABLETAS | C8: 2 | D8: 89 | E8: =D8/1.16 | F8: -0.16 | G8: =D8*0.84 | H8: =G8/1.16 | I8: =C8*G8 | J8: 45323
A9: 503635000200 | B9: JUSTCOLLAGEN POLVO 210 GRS | C9: 2 | D9: 349 | E9: =D9/1.16 | F9: -0.5 | G9: =D9*0.5 | H9: =G9/1.16 | I9: =C9*G9 | J9: 45200
B10: ARISTOCAPS 30 CAPS | C10: 2 | D10: 174 | E10: 174 | F10: -0.43 | G10: =D10*0.57 | H10: 99.18 | I10: =C10*G10 | J10: 45444

Sheet Precios (3)
A1: LISTADO DE PRECIOS E-COMM | E1: -30% Buen Fin
A2: PLATAFORMA | B2: PRODUCTO | C2: Precio de facturación | D2: Precio de venta | E2: Precio de facturación | F2: Precio de venta
A3: AMAZON PRIME | B3: COLAGENO EN POLVO 210 GR | C3: =D3/1.16 | D3: 385 | E3: =F3/1.16 | F3: =D3*0.7
A4: AMAZON PRIME | B4: COLAGENO TIPO II 90 CAPS | C4: =D4/1.16 | D4: 997 | E4: =F4/1.16 | F4: =D4*0.7
A5: AMAZON PRIME | B5: GLUCOSAMINA / CONDROITINA BOVINO 410 TAB | C5: =D5/1.16 | D5: 943 | E5: =F5/1.16 | F5: =D5*0.7
A6: AMAZON PRIME | B6: JUSTBIOH 110 GOMAS | C6: =D6/1.16 | D6: 443 | E6: =F6/1.16 | F6: =D6*0.7
A7: AMAZON PRIME | B7: JUSTBIOTICS 110 GOMAS | C7: =D7/1.16 | D7: 409 | E7: =F7/1.16 | F7: =D7*0.7
A8: AMAZON PRIME | B8: JUSTCOLLAGEN 111 GOMAS | C8: =D8/1.16 | D8: 390 | E8: =F8/1.16 | F8: =D8*0.7
A9: AMAZON PRIME | B9: JUSTOMEGA-3 110 GOMAS | C9: =D9/1.16 | D9: 390 | E9: =F9/1.16 | F9: =D9*0.7
A10: AMAZON PRIME | B10: JUSTCOLLAGEN 180 TABS | C10: =D10/1.16 | D10: 395 | E10: =F10/1.16 | F10: =D10*0.7
A11: AMAZON PRIME | B11: JUSTFX 120 CAPS | C11: =D11/1.16 | D11: 507 | E11: =F11/1.16 | F11: =D11*0.7
A12: AMAZON PRIME | B12: PROBIOTICOS GUMMYCARE 60 GOMAS | C12: =D12/1.16 | D12: 363 | E12: =F12/1.16 | F12: =D12*0.7
A13: AMAZON PRIME | B13: COLÁGENO+BIOTINA 120 GOMAS | C13: =D13/1.16 | D13: 280 | E13: =F13/1.16 | F13: =D13*0.7
A14: AMAZON PRIME | B14: PROBIÓTICOS+FIBRA 120 GOMAS | C14: =D14/1.16 | D14: 280 | E14: =F14/1.16 | F14: =D14*0.7
... A35: AMAZON VENDEDOR | B35: JUSTOLFOCUS 90 CAPS | C35: =D35/1.16 | D35: 493 | E35: =F35/1.16 | F35: =D35*0.7
A36: AMAZON VENDEDOR | B36: KIT BEST SELLER (-10%) | C36: =D36/1.16 | D36: 811.8 | E36: - | F36: -
A37: MERCADO LIBRE | B37: COLAGENO EN POLVO 210 GR | C37: =D37/1.16 | D37: 379 | E37: =F37/1.16 | F37: =D37*0.7
A38: MERCADO LIBRE | B38: COLAGENO TIPO II 90 CAPS | C38: =D38/1.16 | D38: 1063 | E38: =F38/1.16 | F38: =D38*0.7
A39: MERCADO LIBRE | B39: COLAGENO TIPO II 30 CAPS | C39: =D39/1.16 | D39: 547 | E39: =F39/1.16 | F39: =D39*0.7
A40: MERCADO LIBRE | B40: GLUCOSAMINA / CONDROITINA BOVINO 410 TAB | C40: =D40/1.16 | D40: 943 | E40: =F40/1.16 | F40: =D40*0.7
A41: MERCADO LIBRE | B41: GLUCOSAMINA / CONDROITINA TIBURON 240 TA | C41: =D41/1.16 | D41: 597.01 | E41: =F41/1.16 | F41: =D41*0.7
A42: MERCADO LIBRE | B42: JUSTBIOH 110 GOMAS | C42: =D42/1.16 | D42: 443 | E42: =F42/1.16 | F42: =D42*0.7
A43: MERCADO LIBRE | B43: JUSTBIOTICS 110 GOMAS | C43: =D43/1.16 | D43: 409 | E43: =F43/1.16 | F43: =D43*0.7
A44: MERCADO LIBRE | B44: JUSTCETRUX 180 | C44: 219.83 | D44: 199 | E44: =F44/1.16 | F44: =D44*0.7
A45: MERCADO LIBRE | B45: JUSTCETRUX 60 | C45: 107.76 | D45: 97 | E45: - | F45: -
A46: MERCADO LIBRE | B46: JUSTCOLLAGEN 111 GOMAS | C46: =D46/1.16 | D46: 390 | E46: =F46/1.16 | F46: =D46*0.7
A47: MERCADO LIBRE | B47: JUSTCOLLAGEN 180 TABS | C47: =D47/1.16 | D47: 395 | E47: =F47/1.16 | F47: =D47*0.7
A48: MERCADO LIBRE | B48: JUSTCOLLAGEN 90 TABS | C48: =D48/1.16 | D48: 255.2 | E48: =F48/1.16 | F48: =D48*0.7
A49: MERCADO LIBRE | B49: JUSTFX 120 CAPS | C49: =D49/1.16 | D49: 507 | E49: =F49/1.16 | F49: =D49*0.7
A50: MERCADO LIBRE | B50: JUSTFX 90 CAPS | C50: =D50/1.16 | D50: 399.01 | E50: =F50/1.16 | F50: =D50*0.7
A51: MERCADO LIBRE | B51: JUSTOLFOCUS 90 CAPS | C51: =D51/1.16 | D51: 493 | E51: =F51/1.16 | F51: =D51*0.7
A52: MERCADO LIBRE | B52: JUSTOMEGA-3 110 GOMAS | C52: =D52/1.16 | D52: 390 | E52: =F52/1.16 | F52: =D52*0.7
A53: MERCADO LIBRE | B53: PROBIOTICOS GUMMYCARE 60 GOMAS | C53: =D53/1.16 | D53: 375 | E53: =F53/1.16 | F53: =D53*0.7
A54: MERCADO LIBRE | B54: Kit De Colágeno Hidrolizado: Polvo + Gomitas + Tabletas | C54: =D54/1.16 | D54: 1047.6 | E54: - | F54: -
A55: MERCADO LIBRE | B55: KIT GOMITAS | C55: =D55/1.16 | D55: 1070.11 | E55: - | F55: -
A56: MERCADO LIBRE | B56: Kit Gomitas De Colágeno + Biotina | C56: =D56/1.16 | D56: 645.06 | E56: - | F56: -
A57: MERCADO LIBRE | B57: PACK GLUCOSAMINA 240 2PZS | C57: =D57/1.16 | D57: 1134.31 | E57: - | F57: -
A58: MERCADO LIBRE | B58: PACK BIOTINA 110 GOMAS 2PZS | C58: =D58/1.16 | D58: 841.71 | E58: - | F58: -
A59: MERCADO LIBRE | B59: PACK JUSTCOLLAGEN 111 GOMAS 2PZS | C59: =D59/1.16 | D59: 741.01 | E59: - | F59: -
A60: MERCADO LIBRE | B60: Kit Probióticos + Omega, 120 Gomitas | C60: =D60/1.16 | D60: 549.1 | E60: - | F60: -
A61: MERCADO LIBRE | B61: COLÁGENO+BIOTINA 120 GOMAS | C61: =D61/1.16 | D61: 288 | E61: =F61/1.16 | F61: =D61*0.7
A62: MERCADO LIBRE | B62: PROBIÓTICOS+FIBRA 120 GOMAS | C62: =D62/1.16 | D62: 289 | E62: =F62/1.16 | F62: =D62*0.7
A63: MERCADO LIBRE | B63: OMEGA3 DHA 120 GOMAS | C63: =D63/1.16 | D63: 289 | E63: =F63/1.16 | F63: =D63*0.7
A64: MERCADO LIBRE | B64: BIOTINA 120 GOMAS | C64: =D64/1.16 | D64: 289 | E64: =F64/1.16 | F64: =D64*0.7
A65: WEB | B65: COLAGENO EN POLVO 210 GR | C65: =D65/1.16 | D65: 349 | E65: =F65/1.16 | F65: =D65*0.7
A66: WEB | B66: COLAGENO TIPO II 90 CAPS | C66: =D66/1.16 | D66: 1059 | E66: =F66/1.16 | F66: =D66*0.7
A67: WEB | B67: COLAGENO TIPO II 30 CAPS | C67: =D67/1.16 | D67: 509 | E67: =F67/1.16 | F67: =D67*0.7
A68: WEB | B68: GLUCOSAMINA / CONDROITINA TIBURON 160 TA | C68: =D68/1.16 | D68: 499 | E68: =F68/1.16 | F68: =D68*0.7
A69: WEB | B69: GLUCOSAMINA / CONDROITINA TIBURON 240 TA | C69: =D69/1.16 | D69: 595 | E69: =F69/1.16 | F69: =D69*0.7
A70: WEB | B70: GLUCOSAMINA / CONDROITINA BOVINO 410 TAB | C70: =D70/1.16 | D70: 940 | E70: =F70/1.16 | F70: =D70*0.7
A71: WEB | B71: JUSTBIOH 110 GOMAS | C71: =D71/1.16 | D71: 441 | E71: =F71/1.16 | F71: =D71*0.7
A72: WEB | B72: JUSTBIOTICS 110 GOMAS | C72: =D72/1.16 | D72: 407 | E72: =F72/1.16 | F72: =D72*0.7
A73: WEB | B73: JUSTCETRUX 180 | C73: 206.035 | D73: 199 | E73: =F73/1.16 | F73: =D73*0.7
A74: WEB | B74: JUSTCETRUX 60 | C74: 105.17 | D74: 89 | E74: - | F74: -
A75: WEB | B75: JUSTCOLLAGEN 111 GOMAS | C75: =D75/1.16 | D75: 389 | E75: =F75/1.16 | F75: =D75*0.7
A76: WEB | B76: JUSTCOLLAGEN 180 TABS | C76: =D76/1.16 | D76: 395 | E76: =F76/1.16 | F76: =D76*0.7
A77: WEB | B77: JUSTCOLLAGEN 90 TABS | C77: =D77/1.16 | D77: 220 | E77: =F77/1.16 | F77: =D77*0.7
A78: WEB | B78: JUSTFX 120 CAPS | C78: =D78/1.16 | D78: 505 | E78: =F78/1.16 | F78: =D78*0.7
A79: WEB | B79: JUSTFX 90 CAPS | C79: =D79/1.16 | D79: 369 | E79: =F79/1.16 | F79: =D79*0.7
A80: WEB | B80: JUSTOLFOCUS 90 CAPS | C80: =D80/1.16 | D80: 489 | E80: =F80/1.16 | F80: =D80*0.7
A81: WEB | B81: JUSTCALOSTRO 30 CAPS | C81: =D81/1.16 | D81: 167 | E81: - | F81: -
A82: WEB | B82: JUSTOMEGA-3 110 GOMAS | C82: =D82/1.16 | D82: 390 | E82: =F82/1.16 | F82: =D82*0.7
A83: WEB | B83: PROBIOTICOS GUMMYCARE 60 GOMAS | C83: =D83/1.16 | D83: 349 | E83: =F83/1.16 | F83: =D83*0.7
A84: WEB | B84: SISTEMA BELLEZA (-10%) | C84: =D84/1.16 | D84: 1019.7 | E84: - | F84: -
A85: WEB | B85: SISTEMA DEPORTE (-10%) | C85: =D85/1.16 | D85: 1218.6 | E85: - | F85: -
A86: WEB | B86: SISTEMA BEST SELLER (-10%) | C86: =D86/1.16 | D86: 810 | E86: - | F86: -
A87: WEB | B87: PACK 2 PZS COLAGENO TIPO II | C87: =D87/1.16 | D87: 2012.1 | E87: - | F87: -
A88: WEB | B88: PACK 2 PZS GLUCOSAMINA 240 | C88: =D88/1.16 | D88: 1130.5 | E88: - | F88: -
A89: WEB | B89: PACK 2 PZS JUSTBIOH 110 GOMAS | C89: =D89/1.16 | D89: 837.89 | E89: - | F89: -
A90: WEB | B90: PACK 2 PZS JUSTCOLLAGEN 111 GOMAS | C90: =D90/1.16 | D90: 739.1 | E90: - | F90: -
A91: WEB | B91: PACK 2 PZS JUSTCOLLAGEN 180 | C91: =D91/1.16 | D91: 750.51 | E91: - | F91: -
A92: WEB | B92: PACK 2 PZS JUSTFX 120 CAPS | C92: =D92/1.16 | D92: 959.5 | E92: - | F92: -
A93: WEB | B93: PACK 2 PZS JUSTOMEGA3 110 GOMAS | C93: =D93/1.16 | D93: 741 | E93: - | F93: -
A94: WEB | B94: KIT PROBIOTICOS + OMEGA 120 GOMAS | C94: =D94/1.16 | D94: 507.29 | E94: - | F94: -
A95: WEB | B95: KIT GOMITAS DE COLÁGENO + BIOTINA | C95: =D95/1.16 | D95: 623.2 | E95: - | F95: -

Sheet Historial
A1: FechaHora | B1: OrdenVenta | C1: ReferenciaCliente | D1: Cliente | E1: DescripcionPedido | F1: Codigo_Articulo | G1: Cantidad | H1: PrecioUnitario | I1: Porcentaje de descuento | J1: Fecha de envio | K1: Comentario
